{
  "config": {
    "columnCount": 2,
    "characterWidth": 25,
    "minLinesPerColumn": 50
  },
  "pages": [
    {
      "number": 0,
      "properties": {
        "image": "saved.tif",
        "bbox": [
          0,
          0,
          2902,
          3557
        ],
        "ppageno": 0
      },
      "lines": [
        {
          "properties": {
            "bbox": [
              1019,
              0,
              1795,
              46
            ],
            "baseline": [
              0,
              1
            ],
            "x_size": 52.794117,
            "x_descenders": 6.7941179,
            "x_ascenders": 13
          },
          "text": "a\n      eu\n      2\n      we\n      Eee\n      0"
        },
        {
          "properties": {
            "bbox": [
              1297,
              57,
              1796,
              94
            ],
            "baseline": [
              0,
              0
            ],
            "x_size": 55,
            "x_descenders": 7,
            "x_ascenders": 14
          },
          "text": "ART\n      52"
        },
        {
          "properties": {
            "bbox": [
              988,
              147,
              1763,
              182
            ],
            "baseline": [
              0,
              -1
            ],
            "x_size": 30,
            "x_descenders": 6,
            "x_ascenders": 8
          },
          "text": "Arthur\n      Edward\n      G.\n      banker,\n      29\n      Wall,\n      h\n      248\n      Presi-",
          "columnIndex": 0,
          "completeText": "Arthur\n      Edward\n      G.\n      banker,\n      29\n      Wall,\n      h\n      248\n      Presi-"
        },
        {
          "properties": {
            "bbox": [
              1057,
              187,
              1247,
              215
            ],
            "baseline": [
              0,
              -5
            ],
            "x_size": 29,
            "x_descenders": 6,
            "x_ascenders": 6
          },
          "text": "dent,\n      B’klyn",
          "columnIndex": 1,
          "completeText": "dent,\n      B’klyn"
        },
        {
          "properties": {
            "bbox": [
              991,
              214,
              1465,
              247
            ],
            "baseline": [
              0,
              -1
            ],
            "x_size": 30,
            "x_descenders": 6,
            "x_ascenders": 9
          },
          "text": "Arthur\n      Henry,\n      uppers,\n      84\n      Gold",
          "columnIndex": 0,
          "completeText": "Arthur\n      Henry,\n      uppers,\n      84\n      Gold"
        },
        {
          "properties": {
            "bbox": [
              991,
              245,
              1560,
              280
            ],
            "baseline": [
              0,
              -3
            ],
            "x_size": 31,
            "x_descenders": 7,
            "x_ascenders": 8
          },
          "text": "Arthur\n      Henry\n      &\n      Co,\n      uppers.\n      84\n      Gold",
          "columnIndex": 0,
          "completeText": "Arthur\n      Henry\n      &\n      Co,\n      uppers.\n      84\n      Gold"
        },
        {
          "properties": {
            "bbox": [
              991,
              277,
              1563,
              310
            ],
            "baseline": [
              0,
              -1
            ],
            "x_size": 29,
            "x_descenders": 5,
            "x_ascenders": 8
          },
          "text": "Arthur\n      James,\n      laborer,\n      h\n      400\n      W.\n      4ist",
          "columnIndex": 0,
          "completeText": "Arthur\n      James,\n      laborer,\n      h\n      400\n      W.\n      4ist"
        },
        {
          "properties": {
            "bbox": [
              992,
              305,
              1651,
              343
            ],
            "baseline": [
              0,
              -1
            ],
            "x_size": 33,
            "x_descenders": 6,
            "x_ascenders": 11
          },
          "text": "‘Arthur\n      James,\n      machinist,\n      62\n      John,\n      h\n      J.C.",
          "columnIndex": 0,
          "completeText": "‘Arthur\n      James,\n      machinist,\n      62\n      John,\n      h\n      J.C."
        },
        {
          "properties": {
            "bbox": [
              993,
              342,
              1547,
              374
            ],
            "baseline": [
              0,
              0
            ],
            "x_size": 29,
            "x_descenders": 6,
            "x_ascenders": 7
          },
          "text": "Arthur\n      James,\n      smith,\n      h\n      613\n      EB.\n      9th.",
          "columnIndex": 0,
          "completeText": "Arthur\n      James,\n      smith,\n      h\n      613\n      EB.\n      9th."
        },
        {
          "properties": {
            "bbox": [
              993,
              369,
              1769,
              406
            ],
            "baseline": [
              0,
              -1
            ],
            "x_size": 33,
            "x_descenders": 7,
            "x_ascenders": 10
          },
          "text": "‘Arthur\n      James\n      W.\n      stationer,\n      57\n      Liberty,\n      h\n      1037",
          "columnIndex": 0,
          "completeText": "‘Arthur\n      James\n      W.\n      stationer,\n      57\n      Liberty,\n      h\n      1037"
        },
        {
          "properties": {
            "bbox": [
              1060,
              413,
              1248,
              437
            ],
            "baseline": [
              0,
              0
            ],
            "x_size": 28.310463,
            "x_descenders": 6.310462,
            "x_ascenders": 6
          },
          "text": "Madison\n      av.",
          "columnIndex": 1,
          "completeText": "Madison\n      av."
        },
        {
          "properties": {
            "bbox": [
              995,
              439,
              1564,
              472
            ],
            "baseline": [
              0,
              -1
            ],
            "x_size": 28,
            "x_descenders": 4,
            "x_ascenders": 8
          },
          "text": "Arthur\n      John,\n      laborer,\n      h\n      312\n      BE.\n      115th",
          "columnIndex": 0,
          "completeText": "Arthur\n      John,\n      laborer,\n      h\n      312\n      BE.\n      115th"
        },
        {
          "properties": {
            "bbox": [
              995,
              473,
              1452,
              504
            ],
            "baseline": [
              0,
              -1
            ],
            "x_size": 29.310463,
            "x_descenders": 6.310462,
            "x_ascenders": 7
          },
          "text": "Arthur\n      John\n      B.\n      hii6\n      EB.\n      26th",
          "columnIndex": 0,
          "completeText": "Arthur\n      John\n      B.\n      hii6\n      EB.\n      26th"
        },
        {
          "properties": {
            "bbox": [
              996,
              503,
              1659,
              538
            ],
            "baseline": [
              0,
              -3
            ],
            "x_size": 30,
            "x_descenders": 7,
            "x_ascenders": 7
          },
          "text": "Arthur\n      Joseph,\n      laburer,\n      h\n      640\n      Eleventh\n      av.",
          "columnIndex": 0,
          "completeText": "Arthur\n      Joseph,\n      laburer,\n      h\n      640\n      Eleventh\n      av."
        },
        {
          "properties": {
            "bbox": [
              997,
              535,
              1596,
              568
            ],
            "baseline": [
              0,
              -1
            ],
            "x_size": 28,
            "x_descenders": 5,
            "x_ascenders": 7
          },
          "text": "Arthur\n      Martha,\n      dressmkr.\n      131\n      W.\n      85th",
          "columnIndex": 0,
          "completeText": "Arthur\n      Martha,\n      dressmkr.\n      131\n      W.\n      85th"
        },
        {
          "properties": {
            "bbox": [
              996,
              568,
              1607,
              601
            ],
            "baseline": [
              0,
              -1
            ],
            "x_size": 29,
            "x_descenders": 5,
            "x_ascenders": 8
          },
          "text": "Arthur\n      Matthew,\n      porter,\n      h\n      131\n      W.\n      85th",
          "columnIndex": 0,
          "completeText": "Arthur\n      Matthew,\n      porter,\n      h\n      131\n      W.\n      85th"
        },
        {
          "properties": {
            "bbox": [
              997,
              600,
              1593,
              633
            ],
            "baseline": [
              0,
              -1
            ],
            "x_size": 28,
            "x_descenders": 4,
            "x_ascenders": 8
          },
          "text": "Arthur\n      Michael.\n      laborer,\n      h\n      206\n      E.\n      59th",
          "columnIndex": 0,
          "completeText": "Arthur\n      Michael.\n      laborer,\n      h\n      206\n      E.\n      59th"
        },
        {
          "properties": {
            "bbox": [
              998,
              633,
              1563,
              667
            ],
            "baseline": [
              0,
              -3
            ],
            "x_size": 31,
            "x_descenders": 7,
            "x_ascenders": 8
          },
          "text": "Arthur\n      Peter,\n      laborer,\n      h\n      544\n      W.\n      48th",
          "columnIndex": 0,
          "completeText": "Arthur\n      Peter,\n      laborer,\n      h\n      544\n      W.\n      48th"
        },
        {
          "properties": {
            "bbox": [
              998,
              666,
              1579,
              698
            ],
            "baseline": [
              0,
              -1
            ],
            "x_size": 30,
            "x_descenders": 6,
            "x_ascenders": 8
          },
          "text": "Arthur\n      Robert,\n      clerk,\n      h\n      241\n      Third\n      av.",
          "columnIndex": 0,
          "completeText": "Arthur\n      Robert,\n      clerk,\n      h\n      241\n      Third\n      av."
        },
        {
          "properties": {
            "bbox": [
              999,
              697,
              1674,
              731
            ],
            "baseline": [
              0,
              -2
            ],
            "x_size": 29,
            "x_descenders": 6,
            "x_ascenders": 7
          },
          "text": "Arthur\n      Samuel,\n      laborer,\n      h\n      635\n      Eleventh\n      av.",
          "columnIndex": 0,
          "completeText": "Arthur\n      Samuel,\n      laborer,\n      h\n      635\n      Eleventh\n      av."
        },
        {
          "properties": {
            "bbox": [
              999,
              730,
              1649,
              762
            ],
            "baseline": [
              0,
              0
            ],
            "x_size": 28,
            "x_descenders": 4,
            "x_ascenders": 8
          },
          "text": "Arthur\n      Samuel,\n      seainan,\n      h\n      691\n      Second\n      av.",
          "columnIndex": 0,
          "completeText": "Arthur\n      Samuel,\n      seainan,\n      h\n      691\n      Second\n      av."
        },
        {
          "properties": {
            "bbox": [
              1000,
              758,
              1772,
              795
            ],
            "baseline": [
              0,
              -1
            ],
            "x_size": 31,
            "x_descenders": 6,
            "x_ascenders": 9
          },
          "text": "‘Arthur\n      Samuel\n      D.\n      butter,\n      61\n      Clinton\n      mkt,\n      h\n      J.C.",
          "columnIndex": 0,
          "completeText": "‘Arthur\n      Samuel\n      D.\n      butter,\n      61\n      Clinton\n      mkt,\n      h\n      J.C."
        },
        {
          "properties": {
            "bbox": [
              1000,
              794,
              1640,
              827
            ],
            "baseline": [
              0,
              0
            ],
            "x_size": 30,
            "x_descenders": 6,
            "x_ascenders": 8
          },
          "text": "‘Arthur\n      William\n      C,\n      182\n      B'way,\n      h\n      Grand\n      h,",
          "columnIndex": 0,
          "completeText": "‘Arthur\n      William\n      C,\n      182\n      B'way,\n      h\n      Grand\n      h,"
        },
        {
          "properties": {
            "bbox": [
              1000,
              822,
              1775,
              860
            ],
            "baseline": [
              0,
              -1
            ],
            "x_size": 33,
            "x_descenders": 8,
            "x_ascenders": 9
          },
          "text": "‘Arthur\n      William\n      H.\n      stationer,\n      57\n      Liberty,\n      h\n      1037",
          "columnIndex": 0,
          "completeText": "‘Arthur\n      William\n      H.\n      stationer,\n      57\n      Liberty,\n      h\n      1037"
        },
        {
          "properties": {
            "bbox": [
              1067,
              866,
              1255,
              891
            ],
            "baseline": [
              0,
              -1
            ],
            "x_size": 29.310463,
            "x_descenders": 6.310462,
            "x_ascenders": 7
          },
          "text": "Madison\n      av.",
          "columnIndex": 1,
          "completeText": "Madison\n      av."
        },
        {
          "properties": {
            "bbox": [
              1002,
              891,
              1622,
              925
            ],
            "baseline": [
              0,
              -1
            ],
            "x_size": 32,
            "x_descenders": 8,
            "x_ascenders": 8
          },
          "text": "Arthur\n      &\n      Bonnell,\n      stationers,\n      57\n      Liberty",
          "columnIndex": 0,
          "completeText": "Arthur\n      &\n      Bonnell,\n      stationers,\n      57\n      Liberty"
        },
        {
          "properties": {
            "bbox": [
              1002,
              924,
              1558,
              957
            ],
            "baseline": [
              0,
              0
            ],
            "x_size": 28,
            "x_descenders": 5,
            "x_ascenders": 7
          },
          "text": "Arthur\n      &\n      Carr,\n      machinists,\n      62\n      John",
          "columnIndex": 0,
          "completeText": "Arthur\n      &\n      Carr,\n      machinists,\n      62\n      John"
        },
        {
          "properties": {
            "bbox": [
              1004,
              956,
              1582,
              990
            ],
            "baseline": [
              0,
              -1
            ],
            "x_size": 28,
            "x_descenders": 5,
            "x_ascenders": 7
          },
          "text": "Arthur\n      &\n      Ketchum.\n      bankers,\n      29\n      Wall",
          "columnIndex": 0,
          "completeText": "Arthur\n      &\n      Ketchum.\n      bankers,\n      29\n      Wall"
        },
        {
          "properties": {
            "bbox": [
              1003,
              980,
              1781,
              1025
            ],
            "baseline": [
              0,
              -3
            ],
            "x_size": 32,
            "x_descenders": 6,
            "x_ascenders": 9
          },
          "text": "Arthur,\n      Phelps,\n      Knevals\n      &\n      Ransom,\n      lawyers,\n      155",
          "columnIndex": 0,
          "completeText": "Arthur,\n      Phelps,\n      Knevals\n      &\n      Ransom,\n      lawyers,\n      155"
        },
        {
          "properties": {
            "bbox": [
              1069,
              1030,
              1162,
              1057
            ],
            "baseline": [
              0,
              -4
            ],
            "x_size": 30,
            "x_descenders": 7,
            "x_ascenders": 8
          },
          "text": "Bway",
          "columnIndex": 1,
          "completeText": "Bway"
        },
        {
          "properties": {
            "bbox": [
              1004,
              1050,
              1782,
              1088
            ],
            "baseline": [
              0,
              -1
            ],
            "x_size": 30,
            "x_descenders": 5,
            "x_ascenders": 8
          },
          "text": "Arthurs\n      Margaret,\n      wid.\n      William,\n      h\n      r\n      411\n      W.\n      38th",
          "columnIndex": 0,
          "completeText": "Arthurs\n      Margaret,\n      wid.\n      William,\n      h\n      r\n      411\n      W.\n      38th"
        },
        {
          "properties": {
            "bbox": [
              1005,
              1085,
              1607,
              1121
            ],
            "baseline": [
              0,
              -2
            ],
            "x_size": 30,
            "x_descenders": 6,
            "x_ascenders": 8
          },
          "text": "Artman\n      Eginhartt\n      F.\n      artist,\n      332\n      E.\n      9th",
          "columnIndex": 0,
          "completeText": "Artman\n      Eginhartt\n      F.\n      artist,\n      332\n      E.\n      9th"
        },
        {
          "properties": {
            "bbox": [
              1005,
              1115,
              1784,
              1153
            ],
            "baseline": [
              0,
              -2
            ],
            "x_size": 31,
            "x_descenders": 6,
            "x_ascenders": 9
          },
          "text": "‘Artmann\n      Rich.\n      painter,\n      966\n      Sixth\n      av.\n      h\n      442\n      E,\n      88th",
          "columnIndex": 0,
          "completeText": "‘Artmann\n      Rich.\n      painter,\n      966\n      Sixth\n      av.\n      h\n      442\n      E,\n      88th"
        },
        {
          "properties": {
            "bbox": [
              1006,
              1151,
              1710,
              1186
            ],
            "baseline": [
              0,
              -2
            ],
            "x_size": 32,
            "x_descenders": 8,
            "x_ascenders": 8
          },
          "text": "‘Artmann\n      &\n      Fechteler,\n      painters,\n      966\n      Sixth\n      av.",
          "columnIndex": 0,
          "completeText": "‘Artmann\n      &\n      Fechteler,\n      painters,\n      966\n      Sixth\n      av."
        },
        {
          "properties": {
            "bbox": [
              1005,
              1184,
              1633,
              1222
            ],
            "baseline": [
              0,
              -4
            ],
            "x_size": 31,
            "x_descenders": 7,
            "x_ascenders": 7
          },
          "text": "Artopoeus\n      Alexander,\n      mats,\n      221\n      William",
          "columnIndex": 0,
          "completeText": "Artopoeus\n      Alexander,\n      mats,\n      221\n      William"
        },
        {
          "properties": {
            "bbox": [
              1009,
              1221,
              1375,
              1254
            ],
            "baseline": [
              0,
              -4
            ],
            "x_size": 31,
            "x_descenders": 6,
            "x_ascenders": 8
          },
          "text": "*Artotype\n      Co.\n      58\n      Reade",
          "columnIndex": 0,
          "completeText": "*Artotype\n      Co.\n      58\n      Reade"
        },
        {
          "properties": {
            "bbox": [
              1008,
              1250,
              1559,
              1282
            ],
            "baseline": [
              0,
              0
            ],
            "x_size": 31.704866,
            "x_descenders": 6.7048659,
            "x_ascenders": 8
          },
          "text": "Artus\n      Herman,\n      clerk,\n      h\n      543\n      G'wich",
          "columnIndex": 0,
          "completeText": "Artus\n      Herman,\n      clerk,\n      h\n      543\n      G'wich"
        },
        {
          "properties": {
            "bbox": [
              1008,
              1279,
              1788,
              1317
            ],
            "baseline": [
              0,
              -2
            ],
            "x_size": 33,
            "x_descenders": 7,
            "x_ascenders": 9
          },
          "text": "Arundell\n      Jas.\n      F.\n      oysters,\n      209\n      Duane,\n      h\n      150\n      W.\n      16th",
          "columnIndex": 0,
          "completeText": "Arundell\n      Jas.\n      F.\n      oysters,\n      209\n      Duane,\n      h\n      150\n      W.\n      16th"
        },
        {
          "properties": {
            "bbox": [
              1008,
              1315,
              1678,
              1349
            ],
            "baseline": [
              0,
              -2
            ],
            "x_size": 30,
            "x_descenders": 6,
            "x_ascenders": 8
          },
          "text": "Arvidson\n      Andrew,\n      pianomkr.\n      h\n      246\n      E.\n      41st",
          "columnIndex": 0,
          "completeText": "Arvidson\n      Andrew,\n      pianomkr.\n      h\n      246\n      E.\n      41st"
        },
        {
          "properties": {
            "bbox": [
              1009,
              1346,
              1742,
              1384
            ],
            "baseline": [
              0,
              -4
            ],
            "x_size": 30,
            "x_descenders": 6,
            "x_ascenders": 7
          },
          "text": "Arzberger\n      Sebastian,\n      segarmkr,\n      h\n      r\n      176\n      Second",
          "columnIndex": 0,
          "completeText": "Arzberger\n      Sebastian,\n      segarmkr,\n      h\n      r\n      176\n      Second"
        },
        {
          "properties": {
            "bbox": [
              1011,
              1381,
              1496,
              1417
            ],
            "baseline": [
              0,
              -3
            ],
            "x_size": 32,
            "x_descenders": 7,
            "x_ascenders": 8
          },
          "text": "Arzt\n      Adolph,\n      beer,\n      437\n      W.\n      50th",
          "columnIndex": 0,
          "completeText": "Arzt\n      Adolph,\n      beer,\n      437\n      W.\n      50th"
        },
        {
          "properties": {
            "bbox": [
              1010,
              1414,
              1593,
              1450
            ],
            "baseline": [
              0,
              -4
            ],
            "x_size": 31,
            "x_descenders": 7,
            "x_ascenders": 8
          },
          "text": "Arzt\n      David,\n      segarmkr.\n      h\n      111\n      Orchard",
          "columnIndex": 0,
          "completeText": "Arzt\n      David,\n      segarmkr.\n      h\n      111\n      Orchard"
        },
        {
          "properties": {
            "bbox": [
              1011,
              1443,
              1791,
              1480
            ],
            "baseline": [
              0,
              -2
            ],
            "x_size": 32,
            "x_descenders": 6,
            "x_ascenders": 9
          },
          "text": "‘Arzt\n      Frederick,\n      diemkr.\n      Fourth\n      av.\n      c\n      E.\n      834,\n      h",
          "columnIndex": 0,
          "completeText": "‘Arzt\n      Frederick,\n      diemkr.\n      Fourth\n      av.\n      c\n      E.\n      834,\n      h"
        },
        {
          "properties": {
            "bbox": [
              1077,
              1476,
              1253,
              1510
            ],
            "baseline": [
              0,
              0
            ],
            "x_size": 41.071289,
            "x_descenders": 9.0712891,
            "x_ascenders": 9
          },
          "text": "229\n      B.\n      Toth"
        },
        {
          "properties": {
            "bbox": [
              1011,
              1511,
              1644,
              1546
            ],
            "baseline": [
              0,
              -2
            ],
            "x_size": 31,
            "x_descenders": 6,
            "x_ascenders": 8
          },
          "text": "Arzt\n      Frederick\n      jr.\n      diemkr,\n      h\n      229\n      E.\n      (Sth",
          "columnIndex": 0,
          "completeText": "Arzt\n      Frederick\n      jr.\n      diemkr,\n      h\n      229\n      E.\n      (Sth"
        },
        {
          "properties": {
            "bbox": [
              1013,
              1545,
              1741,
              1579
            ],
            "baseline": [
              0,
              -3
            ],
            "x_size": 31,
            "x_descenders": 6,
            "x_ascenders": 9
          },
          "text": "Arzt\n      Gustav,\n      diemkr.\n      h\n      229\n      B,\n      TSth\n      .",
          "columnIndex": 0,
          "completeText": "Arzt\n      Gustav,\n      diemkr.\n      h\n      229\n      B,\n      TSth\n      ."
        },
        {
          "properties": {
            "bbox": [
              1015,
              1573,
              1795,
              1609
            ],
            "baseline": [
              0,
              0
            ],
            "x_size": 35,
            "x_descenders": 9,
            "x_ascenders": 9
          },
          "text": "*Asahel\n      Waukesha\n      Mineral\n      Spring\n      Water,\n      291",
          "columnIndex": 0,
          "completeText": "*Asahel\n      Waukesha\n      Mineral\n      Spring\n      Water,\n      291"
        },
        {
          "properties": {
            "bbox": [
              1079,
              1618,
              1173,
              1646
            ],
            "baseline": [
              0,
              -5
            ],
            "x_size": 29,
            "x_descenders": 6,
            "x_ascenders": 7
          },
          "text": "Bway"
        },
        {
          "properties": {
            "bbox": [
              1014,
              1643,
              1614,
              1676
            ],
            "baseline": [
              0,
              -1
            ],
            "x_size": 30,
            "x_descenders": 5,
            "x_ascenders": 8
          },
          "text": "Asander\n      Simon,\n      tailor,\n      h\n      r\n      181\n      Clinton",
          "columnIndex": 0,
          "completeText": "Asander\n      Simon,\n      tailor,\n      h\n      r\n      181\n      Clinton"
        },
        {
          "properties": {
            "bbox": [
              1015,
              1676,
              1740,
              1712
            ],
            "baseline": [
              0,
              -4
            ],
            "x_size": 31.806463,
            "x_descenders": 6.5921788,
            "x_ascenders": 8.5
          },
          "text": "Asaroff\n      Philip,\n      clerk,\n      h\n      426\n      BE.\n      16th\n      .",
          "columnIndex": 0,
          "completeText": "Asaroff\n      Philip,\n      clerk,\n      h\n      426\n      BE.\n      16th\n      ."
        },
        {
          "properties": {
            "bbox": [
              1017,
              1707,
              1797,
              1742
            ],
            "baseline": [
              0,
              -1
            ],
            "x_size": 31,
            "x_descenders": 7,
            "x_ascenders": 7
          },
          "text": "Asbestos\n      Felting\n      Co.\n      323\n      Front\n      (see\n      page\n      4,\n      com."
        },
        {
          "properties": {
            "bbox": [
              1077,
              1747,
              1156,
              1782
            ],
            "baseline": [
              0,
              -9
            ],
            "x_size": 30,
            "x_descenders": 6,
            "x_ascenders": 7
          },
          "text": "reg.)"
        },
        {
          "properties": {
            "bbox": [
              1018,
              1772,
              1800,
              1808
            ],
            "baseline": [
              0,
              -1
            ],
            "x_size": 30,
            "x_descenders": 5,
            "x_ascenders": 8
          },
          "text": "Asbestos\n      Fire-Proof\n      Building\n      Co.\n      77.\n      William\n      &"
        },
        {
          "properties": {
            "bbox": [
              1084,
              1812,
              1266,
              1839
            ],
            "baseline": [
              0,
              0
            ],
            "x_size": 31.806463,
            "x_descenders": 6.5921788,
            "x_ascenders": 8.5
          },
          "text": "532\n      W.\n      38th"
        },
        {
          "properties": {
            "bbox": [
              1019,
              1840,
              1594,
              1874
            ],
            "baseline": [
              0,
              -1
            ],
            "x_size": 31,
            "x_descenders": 6,
            "x_ascenders": 8
          },
          "text": "Asbestus\n      Patent\n      Fibre\n      Co.\n      194\n      B’way"
        },
        {
          "properties": {
            "bbox": [
              1020,
              1874,
              1606,
              1911
            ],
            "baseline": [
              0,
              -5
            ],
            "x_size": 31,
            "x_descenders": 7,
            "x_ascenders": 7
          },
          "text": "Asbury\n      F.\n      B.\n      signs,\n      41\n      Dey,\n      h\n      B’klyn"
        },
        {
          "properties": {
            "bbox": [
              1020,
              1906,
              1591,
              1941
            ],
            "baseline": [
              0,
              -2
            ],
            "x_size": 30,
            "x_descenders": 6,
            "x_ascenders": 8
          },
          "text": "Asch\n      Abraham,\n      grocer,\n      194\n      Division"
        },
        {
          "properties": {
            "bbox": [
              1021,
              1939,
              1577,
              1975
            ],
            "baseline": [
              0,
              -3
            ],
            "x_size": 32,
            "x_descenders": 7,
            "x_ascenders": 8
          },
          "text": "Asch\n      Golde,\n      widow,\n      h\n      r\n      95\n      Eldridge",
          "columnIndex": 1,
          "completeText": "Asch\n      Golde,\n      widow,\n      h\n      r\n      95\n      Eldridge"
        },
        {
          "properties": {
            "bbox": [
              1022,
              1968,
              1702,
              2005
            ],
            "baseline": [
              0,
              0
            ],
            "x_size": 30,
            "x_descenders": 4,
            "x_ascenders": 9
          },
          "text": "‘Asch\n      Jacob,\n      furs,\n      643\n      Bway,\n      h\n      249\n      W.\n      48th",
          "columnIndex": 1,
          "completeText": "‘Asch\n      Jacob,\n      furs,\n      643\n      Bway,\n      h\n      249\n      W.\n      48th"
        },
        {
          "properties": {
            "bbox": [
              1023,
              2005,
              1596,
              2042
            ],
            "baseline": [
              0,
              -4
            ],
            "x_size": 33,
            "x_descenders": 8,
            "x_ascenders": 8
          },
          "text": "Asch\n      Jacob,\n      tailor,\n      h\n      867\n      E.\n      Houston",
          "columnIndex": 1,
          "completeText": "Asch\n      Jacob,\n      tailor,\n      h\n      867\n      E.\n      Houston"
        },
        {
          "properties": {
            "bbox": [
              1024,
              2032,
              1803,
              2072
            ],
            "baseline": [
              0,
              -1
            ],
            "x_size": 32,
            "x_descenders": 6,
            "x_ascenders": 9
          },
          "text": "‘Asch\n      Jacob\n      H.\n      physician,\n      41\n      Delancey,\n      h\n      207\n      E.",
          "columnIndex": 1,
          "completeText": "‘Asch\n      Jacob\n      H.\n      physician,\n      41\n      Delancey,\n      h\n      207\n      E."
        },
        {
          "properties": {
            "bbox": [
              1091,
              2078,
              1156,
              2103
            ],
            "baseline": [
              0,
              0
            ],
            "x_size": 31.806463,
            "x_descenders": 6.5921788,
            "x_ascenders": 8.5
          },
          "text": "58th"
        },
        {
          "properties": {
            "bbox": [
              1026,
              2102,
              1555,
              2139
            ],
            "baseline": [
              0,
              -3
            ],
            "x_size": 32,
            "x_descenders": 6,
            "x_ascenders": 9
          },
          "text": "Asch\n      Joseph\n      J.\n      furs.\n      h\n      51\n      W.\n      10th",
          "columnIndex": 1,
          "completeText": "Asch\n      Joseph\n      J.\n      furs.\n      h\n      51\n      W.\n      10th"
        },
        {
          "properties": {
            "bbox": [
              1027,
              2140,
              1433,
              2171
            ],
            "baseline": [
              0,
              -3
            ],
            "x_size": 30,
            "x_descenders": 6,
            "x_ascenders": 8
          },
          "text": "Asch\n      Louis,\n      beer,\n      55\n      Allen",
          "columnIndex": 1,
          "completeText": "Asch\n      Louis,\n      beer,\n      55\n      Allen"
        },
        {
          "properties": {
            "bbox": [
              1028,
              2170,
              1499,
              2203
            ],
            "baseline": [
              0,
              -3
            ],
            "x_size": 30,
            "x_descenders": 6,
            "x_ascenders": 7
          },
          "text": "Asch\n      Marx,\n      tailor,\n      437\n      E.\n      15th",
          "columnIndex": 1,
          "completeText": "Asch\n      Marx,\n      tailor,\n      437\n      E.\n      15th"
        },
        {
          "properties": {
            "bbox": [
              1028,
              2197,
              1759,
              2234
            ],
            "baseline": [
              0,
              0
            ],
            "x_size": 32,
            "x_descenders": 6,
            "x_ascenders": 9
          },
          "text": "‘Asch\n      Mitchell\n      J.\n      mer.\n      115\n      P’way,\n      bh\n      114\n      E,\n      “8th",
          "columnIndex": 1,
          "completeText": "‘Asch\n      Mitchell\n      J.\n      mer.\n      115\n      P’way,\n      bh\n      114\n      E,\n      “8th"
        },
        {
          "properties": {
            "bbox": [
              1029,
              2236,
              1565,
              2270
            ],
            "baseline": [
              0,
              -4
            ],
            "x_size": 31,
            "x_descenders": 7,
            "x_ascenders": 8
          },
          "text": "Asch\n      Moritz,\n      shirts,\n      821\n      Bleecker\n      .",
          "columnIndex": 1,
          "completeText": "Asch\n      Moritz,\n      shirts,\n      821\n      Bleecker\n      ."
        },
        {
          "properties": {
            "bbox": [
              1030,
              2265,
              1642,
              2301
            ],
            "baseline": [
              0,
              -2
            ],
            "x_size": 32,
            "x_descenders": 8,
            "x_ascenders": 8
          },
          "text": "‘Asch\n      Morris\n      J.\n      physician,\n      h\n      23\n      W.\n      30th",
          "columnIndex": 1,
          "completeText": "‘Asch\n      Morris\n      J.\n      physician,\n      h\n      23\n      W.\n      30th"
        },
        {
          "properties": {
            "bbox": [
              1031,
              2301,
              1609,
              2332
            ],
            "baseline": [
              0,
              -1
            ],
            "x_size": 30,
            "x_descenders": 6,
            "x_ascenders": 8
          },
          "text": "Asch\n      Oswald\n      S.\n      carver,\n      h\n      894\n      Broome",
          "columnIndex": 1,
          "completeText": "Asch\n      Oswald\n      S.\n      carver,\n      h\n      894\n      Broome"
        },
        {
          "properties": {
            "bbox": [
              1016,
              2332,
              1582,
              2368
            ],
            "baseline": [
              0,
              -4
            ],
            "x_size": 31,
            "x_descenders": 6,
            "x_ascenders": 9
          },
          "text": "“Asch\n      Siegfried,\n      clerk.\n      h\n      332\n      EH.\n      80th",
          "columnIndex": 0,
          "completeText": "“Asch\n      Siegfried,\n      clerk.\n      h\n      332\n      EH.\n      80th"
        },
        {
          "properties": {
            "bbox": [
              1033,
              2365,
              1713,
              2397
            ],
            "baseline": [
              0,
              -1
            ],
            "x_size": 30,
            "x_descenders": 5,
            "x_ascenders": 8
          },
          "text": "Asch\n      Simon\n      A.\n      mer,\n      132\n      Church,\n      h\n      Panama",
          "columnIndex": 1,
          "completeText": "Asch\n      Simon\n      A.\n      mer,\n      132\n      Church,\n      h\n      Panama"
        },
        {
          "properties": {
            "bbox": [
              1034,
              2398,
              1629,
              2431
            ],
            "baseline": [
              0,
              -2
            ],
            "x_size": 29,
            "x_descenders": 6,
            "x_ascenders": 7
          },
          "text": "Asch\n      Solomon,\n      capmkr.\n      h\n      14\n      Division",
          "columnIndex": 1,
          "completeText": "Asch\n      Solomon,\n      capmkr.\n      h\n      14\n      Division"
        },
        {
          "properties": {
            "bbox": [
              1034,
              2432,
              1523,
              2465
            ],
            "baseline": [
              0,
              -3
            ],
            "x_size": 32,
            "x_descenders": 8,
            "x_ascenders": 8
          },
          "text": "Asch\n      Wolf,\n      cutter,\n      h\n      49\n      Norfolk",
          "columnIndex": 1,
          "completeText": "Asch\n      Wolf,\n      cutter,\n      h\n      49\n      Norfolk"
        },
        {
          "properties": {
            "bbox": [
              1035,
              2463,
              1671,
              2497
            ],
            "baseline": [
              0,
              -2
            ],
            "x_size": 28,
            "x_descenders": 4,
            "x_ascenders": 7
          },
          "text": "Aschauer\n      George,\n      baker,\n      1025\n      Second\n      av.",
          "columnIndex": 1,
          "completeText": "Aschauer\n      George,\n      baker,\n      1025\n      Second\n      av."
        },
        {
          "properties": {
            "bbox": [
              1036,
              2495,
              1681,
              2528
            ],
            "baseline": [
              0,
              -1
            ],
            "x_size": 31,
            "x_descenders": 7,
            "x_ascenders": 8
          },
          "text": "Asche\n      Charles\n      H.\n      broker,\n      42\n      Pine,\n      h\n      L.\n      I.",
          "columnIndex": 1,
          "completeText": "Asche\n      Charles\n      H.\n      broker,\n      42\n      Pine,\n      h\n      L.\n      I."
        },
        {
          "properties": {
            "bbox": [
              1037,
              2527,
              1802,
              2562
            ],
            "baseline": [
              0,
              -2
            ],
            "x_size": 31,
            "x_descenders": 6,
            "x_ascenders": 8
          },
          "text": "Asche\n      Christopher,\n      tailor,\n      h\n      W.\n      116th\n      n\n      Sixth\n      av.",
          "columnIndex": 1,
          "completeText": "Asche\n      Christopher,\n      tailor,\n      h\n      W.\n      116th\n      n\n      Sixth\n      av."
        },
        {
          "properties": {
            "bbox": [
              1038,
              2562,
              1510,
              2595
            ],
            "baseline": [
              0,
              -3
            ],
            "x_size": 30,
            "x_descenders": 6,
            "x_ascenders": 7
          },
          "text": "Ascheim\n      Joseph,\n      h\n      151\n      E.\n      5th",
          "columnIndex": 1,
          "completeText": "Ascheim\n      Joseph,\n      h\n      151\n      E.\n      5th"
        },
        {
          "properties": {
            "bbox": [
              1040,
              2593,
              1654,
              2629
            ],
            "baseline": [
              0,
              -4
            ],
            "x_size": 32,
            "x_descenders": 7,
            "x_ascenders": 9
          },
          "text": "Ascheim\n      Louis,\n      shoemkr.\n      h\n      244\n      W.\n      30th",
          "columnIndex": 1,
          "completeText": "Ascheim\n      Louis,\n      shoemkr.\n      h\n      244\n      W.\n      30th"
        },
        {
          "properties": {
            "bbox": [
              1040,
              2627,
              1620,
              2657
            ],
            "baseline": [
              0,
              0
            ],
            "x_size": 29,
            "x_descenders": 5,
            "x_ascenders": 8
          },
          "text": "Aschein\n      Morris,\n      broker,\n      h\n      243\n      B.\n      34th",
          "columnIndex": 1,
          "completeText": "Aschein\n      Morris,\n      broker,\n      h\n      243\n      B.\n      34th"
        },
        {
          "properties": {
            "bbox": [
              1041,
              2657,
              1791,
              2691
            ],
            "baseline": [
              0,
              -2
            ],
            "x_size": 31,
            "x_descenders": 6,
            "x_ascenders": 8
          },
          "text": "Aschemoor\n      William,\n      liquors,\n      306\n      G’wich,\n      h\n      N.\n      J.",
          "columnIndex": 1,
          "completeText": "Aschemoor\n      William,\n      liquors,\n      306\n      G’wich,\n      h\n      N.\n      J."
        },
        {
          "properties": {
            "bbox": [
              1042,
              2690,
              1815,
              2723
            ],
            "baseline": [
              0,
              -2
            ],
            "x_size": 31,
            "x_descenders": 7,
            "x_ascenders": 8
          },
          "text": "Aschenbach\n      Charles\n      F,\n      harness,\n      7\n      Murray,\n      h\n      N.\n      J.",
          "columnIndex": 1,
          "completeText": "Aschenbach\n      Charles\n      F,\n      harness,\n      7\n      Murray,\n      h\n      N.\n      J."
        },
        {
          "properties": {
            "bbox": [
              1043,
              2721,
              1817,
              2758
            ],
            "baseline": [
              0,
              -5
            ],
            "x_size": 30,
            "x_descenders": 6,
            "x_ascenders": 8
          },
          "text": "Aschenbach\n      George,\n      grocer,\n      Boulevard\n      ¢\n      W.\n      110th",
          "columnIndex": 1,
          "completeText": "Aschenbach\n      George,\n      grocer,\n      Boulevard\n      ¢\n      W.\n      110th"
        },
        {
          "properties": {
            "bbox": [
              1044,
              2756,
              1812,
              2790
            ],
            "baseline": [
              0,
              -4
            ],
            "x_size": 30,
            "x_descenders": 6,
            "x_ascenders": 8
          },
          "text": "Aschenbach\n      Henry,\n      harness,\n      73\n      Warren,\n      hN.\n      J.\n      .",
          "columnIndex": 1,
          "completeText": "Aschenbach\n      Henry,\n      harness,\n      73\n      Warren,\n      hN.\n      J.\n      ."
        },
        {
          "properties": {
            "bbox": [
              1046,
              2789,
              1687,
              2821
            ],
            "baseline": [
              0,
              -4
            ],
            "x_size": 29,
            "x_descenders": 6,
            "x_ascenders": 7
          },
          "text": "*Aschenbach\n      Mfg.\n      Co,\n      harness,\n      7\n      Murray",
          "columnIndex": 1,
          "completeText": "*Aschenbach\n      Mfg.\n      Co,\n      harness,\n      7\n      Murray"
        },
        {
          "properties": {
            "bbox": [
              1046,
              2823,
              1603,
              2854
            ],
            "baseline": [
              0,
              -3
            ],
            "x_size": 30,
            "x_descenders": 6,
            "x_ascenders": 8
          },
          "text": "Aschenbach\n      Philip,\n      beer,\n      225\n      Grand",
          "columnIndex": 1,
          "completeText": "Aschenbach\n      Philip,\n      beer,\n      225\n      Grand"
        },
        {
          "properties": {
            "bbox": [
              1046,
              2855,
              1700,
              2886
            ],
            "baseline": [
              0,
              -3
            ],
            "x_size": 29,
            "x_descenders": 5,
            "x_ascenders": 7
          },
          "text": "Aschenbeck\n      August,\n      tailor,\n      h\n      122\n      Attorney",
          "columnIndex": 1,
          "completeText": "Aschenbeck\n      August,\n      tailor,\n      h\n      122\n      Attorney"
        },
        {
          "properties": {
            "bbox": [
              1047,
              2885,
              1789,
              2918
            ],
            "baseline": [
              0,
              -3
            ],
            "x_size": 30,
            "x_descenders": 5,
            "x_ascenders": 9
          },
          "text": "Aschenbrand\n      Karl,\n      drugs,\n      Courtland\n      av.\n      c\n      155th",
          "columnIndex": 1,
          "completeText": "Aschenbrand\n      Karl,\n      drugs,\n      Courtland\n      av.\n      c\n      155th"
        },
        {
          "properties": {
            "bbox": [
              1049,
              2919,
              1696,
              2950
            ],
            "baseline": [
              0,
              -2
            ],
            "x_size": 30,
            "x_descenders": 6,
            "x_ascenders": 8
          },
          "text": "Aschenbrand\n      Wolf.\n      butcher,\n      h\n      323\n      E.\n      47th",
          "columnIndex": 1,
          "completeText": "Aschenbrand\n      Wolf.\n      butcher,\n      h\n      323\n      E.\n      47th"
        },
        {
          "properties": {
            "bbox": [
              1049,
              2951,
              1765,
              2984
            ],
            "baseline": [
              0,
              -3
            ],
            "x_size": 30,
            "x_descenders": 5,
            "x_ascenders": 9
          },
          "text": "Aschenbrenner\n      William,\n      teacher,\n      h\n      3846\n      E,\n      17th",
          "columnIndex": 1,
          "completeText": "Aschenbrenner\n      William,\n      teacher,\n      h\n      3846\n      E,\n      17th"
        },
        {
          "properties": {
            "bbox": [
              1051,
              2984,
              1540,
              3016
            ],
            "baseline": [
              0,
              -3
            ],
            "x_size": 31,
            "x_descenders": 7,
            "x_ascenders": 8
          },
          "text": "Aschenbroedel\n      Verein,\n      74\n      E.\n      4th",
          "columnIndex": 1,
          "completeText": "Aschenbroedel\n      Verein,\n      74\n      E.\n      4th"
        },
        {
          "properties": {
            "bbox": [
              1051,
              3016,
              1822,
              3049
            ],
            "baseline": [
              0,
              -4
            ],
            "x_size": 31,
            "x_descenders": 7,
            "x_ascenders": 8
          },
          "text": "Ascher\n      Adolph,\n      lawyer,\n      320\n      B’way,h\n      939\n      Second\n      av.",
          "columnIndex": 1,
          "completeText": "Ascher\n      Adolph,\n      lawyer,\n      320\n      B’way,h\n      939\n      Second\n      av."
        },
        {
          "properties": {
            "bbox": [
              1052,
              3048,
              1761,
              3087
            ],
            "baseline": [
              0,
              -10
            ],
            "x_size": 31,
            "x_descenders": 7,
            "x_ascenders": 8
          },
          "text": "Ascher\n      Alex,\n      8.\n      cloaks,\n      39\n      White,\n      h\n      23\n      W.\n      24th",
          "columnIndex": 1,
          "completeText": "Ascher\n      Alex,\n      8.\n      cloaks,\n      39\n      White,\n      h\n      23\n      W.\n      24th"
        },
        {
          "properties": {
            "bbox": [
              1802,
              0,
              2508,
              38
            ],
            "baseline": [
              0,
              -4
            ],
            "x_size": 45,
            "x_descenders": 11,
            "x_ascenders": 10
          },
          "text": "9\n      UNION\n      oGUall;\n      &\n      Asan"
        },
        {
          "properties": {
            "bbox": [
              2157,
              41,
              2259,
              77
            ],
            "baseline": [
              0,
              0
            ],
            "x_size": 46.5,
            "x_descenders": 11.5,
            "x_ascenders": 10.5
          },
          "text": "ASII"
        },
        {
          "properties": {
            "bbox": [
              2224,
              96,
              2571,
              108
            ],
            "baseline": [
              0,
              -5
            ],
            "x_size": 20,
            "x_descenders": 5,
            "x_ascenders": 5
          },
          "text": "ee"
        },
        {
          "properties": {
            "bbox": [
              1802,
              357,
              2381,
              396
            ],
            "baseline": [
              0,
              -3
            ],
            "x_size": 30,
            "x_descenders": 7,
            "x_ascenders": 7
          },
          "text": "‘Ascher\n      &\n      Paynter,\n      printers,\n      381\n      Pearl"
        },
        {
          "properties": {
            "bbox": [
              1803,
              388,
              2472,
              426
            ],
            "baseline": [
              0,
              -1
            ],
            "x_size": 31,
            "x_descenders": 8,
            "x_ascenders": 7
          },
          "text": "‘Aschermann\n      Rudolph,\n      tailor,\n      h\n      73\n      Orchard"
        },
        {
          "properties": {
            "bbox": [
              1803,
              425,
              2319,
              458
            ],
            "baseline": [
              0,
              -1
            ],
            "x_size": 31.048613,
            "x_descenders": 7.0486126,
            "x_ascenders": 8
          },
          "text": "Ascherson\n      Edward,\n      iron,\n      99\n      John"
        },
        {
          "properties": {
            "bbox": [
              1803,
              454,
              2466,
              490
            ],
            "baseline": [
              0,
              0
            ],
            "x_size": 30,
            "x_descenders": 7,
            "x_ascenders": 7
          },
          "text": "‘Ascheuer\n      Frederick,\n      grinder,\n      h\n      116\n      Ludlow"
        },
        {
          "properties": {
            "bbox": [
              1805,
              486,
              2450,
              526
            ],
            "baseline": [
              0,
              -4
            ],
            "x_size": 30,
            "x_descenders": 6,
            "x_ascenders": 8
          },
          "text": "Aschinger\n      Anton,\n      shoemkr.\n      h\n      82\n      Seventh"
        },
        {
          "properties": {
            "bbox": [
              1805,
              519,
              2391,
              556
            ],
            "baseline": [
              0,
              -2
            ],
            "x_size": 31,
            "x_descenders": 7,
            "x_ascenders": 8
          },
          "text": "‘Aschman\n      John,\n      laborer,\n      h\n      244\n      1.\n      44h"
        },
        {
          "properties": {
            "bbox": [
              1805,
              549,
              2535,
              588
            ],
            "baseline": [
              0,
              -1
            ],
            "x_size": 31,
            "x_descenders": 7,
            "x_ascenders": 8
          },
          "text": "Aschner\n      Abraham,\n      segars,\n      $7\n      West,\n      h\n      101\n      West"
        },
        {
          "properties": {
            "bbox": [
              1805,
              585,
              2419,
              621
            ],
            "baseline": [
              0,
              -2
            ],
            "x_size": 29,
            "x_descenders": 5,
            "x_ascenders": 8
          },
          "text": "Aschner\n      Herman,\n      segars,\n      126}¢\n      Liberty"
        },
        {
          "properties": {
            "bbox": [
              1805,
              614,
              2585,
              654
            ],
            "baseline": [
              0,
              -3
            ],
            "x_size": 30,
            "x_descenders": 7,
            "x_ascenders": 7
          },
          "text": "Aschner\n      Sigmund,\n      segarmkr.\n      25\n      Allen,\n      h\n      66\n      For-"
        },
        {
          "properties": {
            "bbox": [
              1871,
              659,
              2152,
              682
            ],
            "baseline": [
              0,
              0
            ],
            "x_size": 29.048613,
            "x_descenders": 7.0486126,
            "x_ascenders": 6
          },
          "text": "syth\n      -"
        },
        {
          "properties": {
            "bbox": [
              1807,
              663,
              2587,
              726
            ],
            "baseline": [
              0,
              -10
            ],
            "x_size": 32,
            "x_descenders": 7,
            "x_ascenders": 9
          },
          "text": "Aschoff\n      Henry\n      W.\n      grocer,\n      93\n      Varick,\n      &\n      liquors,\n      £2"
        },
        {
          "properties": {
            "bbox": [
              1872,
              720,
              2179,
              752
            ],
            "baseline": [
              0,
              -5
            ],
            "x_size": 31,
            "x_descenders": 7,
            "x_ascenders": 8
          },
          "text": "Varick,\n      h\n      92\n      Varick"
        },
        {
          "properties": {
            "bbox": [
              1808,
              748,
              2411,
              783
            ],
            "baseline": [
              0,
              -2
            ],
            "x_size": 31,
            "x_descenders": 7,
            "x_ascenders": 8
          },
          "text": "Aschoff\n      Joseph,\n      barber,\n      19%5\n      Third\n      av."
        },
        {
          "properties": {
            "bbox": [
              1809,
              777,
              2557,
              816
            ],
            "baseline": [
              0,
              -4
            ],
            "x_size": 31,
            "x_descenders": 7,
            "x_ascenders": 8
          },
          "text": "‘Aschoff\n      Lonis,\n      shoes,\n      123\n      Varick.\n      h\n      22\n      Dominick"
        },
        {
          "properties": {
            "bbox": [
              1810,
              811,
              2475,
              850
            ],
            "baseline": [
              0,
              -5
            ],
            "x_size": 30,
            "x_descenders": 6,
            "x_ascenders": 8
          },
          "text": "Ascough\n      Theodore\n      G.\n      clerk,\n      h\n      171\n      W.\n      11th"
        },
        {
          "properties": {
            "bbox": [
              1811,
              844,
              2412,
              881
            ],
            "baseline": [
              0,
              -4
            ],
            "x_size": 31,
            "x_descenders": 7,
            "x_ascenders": 8
          },
          "text": "Asel\n      William,\n      satchelmkr.\n      h\n      270\n      B.\n      4th"
        },
        {
          "properties": {
            "bbox": [
              1812,
              877,
              2491,
              911
            ],
            "baseline": [
              0,
              -1
            ],
            "x_size": 30,
            "x_descenders": 6,
            "x_ascenders": 8
          },
          "text": "Asen\n      Christian,\n      pianomkr.\n      h\n      466\n      Eighth\n      av."
        },
        {
          "properties": {
            "bbox": [
              1813,
              913,
              2307,
              944
            ],
            "baseline": [
              0,
              -2
            ],
            "x_size": 30,
            "x_descenders": 7,
            "x_ascenders": 7
          },
          "text": "Asencio\n      Thomas,\n      mer.\n      40\n      B’way"
        },
        {
          "properties": {
            "bbox": [
              1814,
              944,
              2522,
              980
            ],
            "baseline": [
              0,
              -5
            ],
            "x_size": 31,
            "x_descenders": 8,
            "x_ascenders": 7
          },
          "text": "Asencio,\n      Losada\n      &\n      Co.\n      mers,\n      4U\n      Bway\n      -"
        },
        {
          "properties": {
            "bbox": [
              1815,
              977,
              2358,
              1010
            ],
            "baseline": [
              0,
              -3
            ],
            "x_size": 32,
            "x_descenders": 7,
            "x_ascenders": 9
          },
          "text": "Asendort\n      Herman,\n      h\n      100\n      Ninth\n      av."
        },
        {
          "properties": {
            "bbox": [
              1815,
              1007,
              2418,
              1044
            ],
            "baseline": [
              0,
              -4
            ],
            "x_size": 31,
            "x_descenders": 6,
            "x_ascenders": 9
          },
          "text": "Asfaog\n      Jacob,\n      carpenter,\n      h\n      422\n      F.\n      10th"
        },
        {
          "properties": {
            "bbox": [
              1816,
              1042,
              2382,
              1075
            ],
            "baseline": [
              0,
              -3
            ],
            "x_size": 31,
            "x_descenders": 7,
            "x_ascenders": 8
          },
          "text": "Ash\n      Abraham\n      J.\n      (Rev.)\n      h\n      49\n      Suftolk"
        },
        {
          "properties": {
            "bbox": [
              1816,
              1074,
              2443,
              1108
            ],
            "baseline": [
              0,
              -3
            ],
            "x_size": 30,
            "x_descenders": 6,
            "x_ascenders": 8
          },
          "text": "Ash\n      Anthony,\n      cabinetmkr.\n      h\n      r\n      104\n      Perry"
        },
        {
          "properties": {
            "bbox": [
              1818,
              1105,
              2535,
              1142
            ],
            "baseline": [
              0,
              -5
            ],
            "x_size": 31,
            "x_descenders": 6,
            "x_ascenders": 9
          },
          "text": "Ash\n      Benjamin,\n      segars,\n      96\n      Reade,\n      h\n      141\n      E.\n      49th"
        },
        {
          "properties": {
            "bbox": [
              1819,
              1139,
              2433,
              1175
            ],
            "baseline": [
              0,
              -5
            ],
            "x_size": 31,
            "x_descenders": 7,
            "x_ascenders": 7
          },
          "text": "Ash\n      Clara,\n      wid.\n      Charles,\n      h\n      423\n      W.\n      26th"
        },
        {
          "properties": {
            "bbox": [
              1823,
              1173,
              2439,
              1207
            ],
            "baseline": [
              0,
              -4
            ],
            "x_size": 31,
            "x_descenders": 7,
            "x_ascenders": 8
          },
          "text": "Ash\n      Dora,\n      wid.\n      Elijah,\n      h\n      125\n      G*wich\n      av."
        },
        {
          "properties": {
            "bbox": [
              1819,
              1207,
              2369,
              1239
            ],
            "baseline": [
              0,
              -3
            ],
            "x_size": 31,
            "x_descenders": 6,
            "x_ascenders": 9
          },
          "text": "Ash\n      Edward,\n      porter,\n      h\n      115\n      Sullivan"
        },
        {
          "properties": {
            "bbox": [
              1821,
              1238,
              2324,
              1272
            ],
            "baseline": [
              0,
              -4
            ],
            "x_size": 30,
            "x_descenders": 6,
            "x_ascenders": 8
          },
          "text": "Ash\n      Henry,\n      clerk,\n      h\n      505\n      W.\n      12th"
        },
        {
          "properties": {
            "bbox": [
              1838,
              1959,
              2517,
              1992
            ],
            "baseline": [
              0,
              -3
            ],
            "x_size": 30,
            "x_descenders": 6,
            "x_ascenders": 8
          },
          "text": "Ash\n      Rosa,\n      caps,\n      74\n      &\n      156\n      Greene,\n      h\n      94\n      First"
        },
        {
          "properties": {
            "bbox": [
              1839,
              1993,
              2353,
              2026
            ],
            "baseline": [
              0,
              -3
            ],
            "x_size": 31,
            "x_descenders": 7,
            "x_ascenders": 8
          },
          "text": "Ash\n      Samuel,\n      clerk,\n      h\n      465\n      W.\n      49th"
        },
        {
          "properties": {
            "bbox": [
              1841,
              2025,
              2436,
              2058
            ],
            "baseline": [
              0,
              -3
            ],
            "x_size": 31.865103,
            "x_descenders": 6.4791665,
            "x_ascenders": 8.6044779
          },
          "text": "Ash\n      Sarah,\n      wid.\n      Simon,\n      b\n      305\n      W.\n      13th"
        },
        {
          "properties": {
            "bbox": [
              1840,
              2057,
              2482,
              2090
            ],
            "baseline": [
              0,
              -2
            ],
            "x_size": 31,
            "x_descenders": 7,
            "x_ascenders": 8
          },
          "text": "Ash\n      Thomas,\n      ladders,\n      h\n      64\n      W.\n      Washn.\n      pl."
        },
        {
          "properties": {
            "bbox": [
              1841,
              2091,
              2411,
              2122
            ],
            "baseline": [
              0,
              -1
            ],
            "x_size": 28,
            "x_descenders": 4,
            "x_ascenders": 8
          },
          "text": "Ash\n      Thomas,\n      waiter,\n      h\n      r\n      38\n      Cornelia"
        },
        {
          "properties": {
            "bbox": [
              1841,
              2120,
              2604,
              2156
            ],
            "baseline": [
              0,
              -2
            ],
            "x_size": 31,
            "x_descenders": 5,
            "x_ascenders": 9
          },
          "text": "Ash\n      Thos,\n      T.\n      painter,\n      r555\n      W.\n      42d,\n      h\n      257\n      W.\n      434"
        },
        {
          "properties": {
            "bbox": [
              1843,
              2155,
              2586,
              2191
            ],
            "baseline": [
              0,
              -5
            ],
            "x_size": 31,
            "x_descenders": 6,
            "x_ascenders": 8
          },
          "text": "Ash\n      Timothy,\n      oysters,\n      Pier\n      7\n      E.\n      R.\n      h\n      63\n      Washn."
        },
        {
          "properties": {
            "bbox": [
              1843,
              2188,
              2498,
              2220
            ],
            "baseline": [
              0,
              -1
            ],
            "x_size": 30.177452,
            "x_descenders": 6.1774526,
            "x_ascenders": 8
          },
          "text": "Ash\n      William\n      H.\n      cabinetmkr.\n      h\n      829\n      E.\n      46th"
        },
        {
          "properties": {
            "bbox": [
              1844,
              2222,
              2446,
              2253
            ],
            "baseline": [
              0,
              -1
            ],
            "x_size": 31,
            "x_descenders": 6,
            "x_ascenders": 8
          },
          "text": "Ash\n      L.\n      &\n      J.\n      &\n      Co.\n      clothing,\n      536\n      Bway"
        },
        {
          "properties": {
            "bbox": [
              1845,
              2253,
              2586,
              2285
            ],
            "baseline": [
              0,
              0
            ],
            "x_size": 30,
            "x_descenders": 5,
            "x_ascenders": 9
          },
          "text": "Ash\n      R,\n      &\n      BR.\n      Leidesdorf,\n      caps,\n      78\n      &\n      136\n      Greene’"
        },
        {
          "properties": {
            "bbox": [
              1845,
              2287,
              2456,
              2319
            ],
            "baseline": [
              0,
              -1
            ],
            "x_size": 30,
            "x_descenders": 5,
            "x_ascenders": 8
          },
          "text": "Ash\n      &\n      Buckbee,\n      plumbers,\n      183\n      William"
        },
        {
          "properties": {
            "bbox": [
              1847,
              2317,
              2468,
              2353
            ],
            "baseline": [
              0,
              -3
            ],
            "x_size": 32,
            "x_descenders": 6,
            "x_ascenders": 10
          },
          "text": "Ash\n      &\n      Esler,\n      milk,\n      127\n      E,\n      53a\n      ."
        },
        {
          "properties": {
            "bbox": [
              1848,
              2353,
              2483,
              2385
            ],
            "baseline": [
              0,
              -1
            ],
            "x_size": 31,
            "x_descenders": 7,
            "x_ascenders": 7
          },
          "text": "Ash\n      &\n      Garbage\n      Vault\n      Co.\n      985\n      Eighth\n      av."
        },
        {
          "properties": {
            "bbox": [
              1847,
              2386,
              2517,
              2419
            ],
            "baseline": [
              0,
              -2
            ],
            "x_size": 31,
            "x_descenders": 7,
            "x_ascenders": 8
          },
          "text": "Ashanden\n      William,\n      butcher,\n      h\n      131\n      Orchard"
        },
        {
          "properties": {
            "bbox": [
              1848,
              2419,
              2429,
              2450
            ],
            "baseline": [
              0,
              -1
            ],
            "x_size": 29,
            "x_descenders": 5,
            "x_ascenders": 7
          },
          "text": "Ashback\n      Jacob,\n      porter,\n      h\n      308\n      Hudson"
        },
        {
          "properties": {
            "bbox": [
              1847,
              2450,
              2619,
              2487
            ],
            "baseline": [
              0,
              -4
            ],
            "x_size": 33,
            "x_descenders": 8,
            "x_ascenders": 8
          },
          "text": "Ashbey\n      Asa\n      A.\n      fish,\n      229\n      Washn.\n      mkt,\n      h\n      108\n      Brown,"
        },
        {
          "properties": {
            "bbox": [
              1915,
              2486,
              2294,
              2514
            ],
            "baseline": [
              0,
              0
            ],
            "x_size": 31.865103,
            "x_descenders": 6.4791665,
            "x_ascenders": 8.6044779
          },
          "text": "J.C.\n      :"
        },
        {
          "properties": {
            "bbox": [
              1849,
              2517,
              2428,
              2553
            ],
            "baseline": [
              0,
              -4
            ],
            "x_size": 31,
            "x_descenders": 6,
            "x_ascenders": 8
          },
          "text": "Ashbey\n      George,\n      pedlar,\n      h\n      120\n      E.\n      11th"
        },
        {
          "properties": {
            "bbox": [
              1849,
              2550,
              2420,
              2586
            ],
            "baseline": [
              0,
              -4
            ],
            "x_size": 29,
            "x_descenders": 5,
            "x_ascenders": 8
          },
          "text": "Ashbey\n      Robert,\n      pedlar,\n      h\n      12U\n      BE,\n      11th"
        },
        {
          "properties": {
            "bbox": [
              1849,
              2583,
              2487,
              2615
            ],
            "baseline": [
              0,
              0
            ],
            "x_size": 28,
            "x_descenders": 5,
            "x_ascenders": 7
          },
          "text": "Ashburner\n      Wiiliam.\n      pres.\n      18\n      Wall.\n      h\n      Cal."
        },
        {
          "properties": {
            "bbox": [
              1850,
              2616,
              2496,
              2653
            ],
            "baseline": [
              0,
              -6
            ],
            "x_size": 33,
            "x_descenders": 9,
            "x_ascenders": 8
          },
          "text": "Ashby\n      Cornelius,\n      weaver,\n      h\n      593\n      Ninth\n      av."
        },
        {
          "properties": {
            "bbox": [
              1849,
              2649,
              2437,
              2686
            ],
            "baseline": [
              0,
              -6
            ],
            "x_size": 28,
            "x_descenders": 4,
            "x_ascenders": 8
          },
          "text": "Ashby\n      Henry.\n      porter,\n      h\n      769\n      Ninth\n      av,"
        },
        {
          "properties": {
            "bbox": [
              1851,
              2679,
              2624,
              2718
            ],
            "baseline": [
              0,
              -4
            ],
            "x_size": 32,
            "x_descenders": 7,
            "x_ascenders": 9
          },
          "text": "Ashby\n      James\n      J.\n      laundry,\n      5\n      Thompson,\n      h\n      15\n      St."
        },
        {
          "properties": {
            "bbox": [
              1916,
              2719,
              2064,
              2749
            ],
            "baseline": [
              0,
              -3
            ],
            "x_size": 31,
            "x_descenders": 7,
            "x_ascenders": 7
          },
          "text": "Luke's\n      pl."
        },
        {
          "properties": {
            "bbox": [
              1852,
              2747,
              2496,
              2781
            ],
            "baseline": [
              0,
              -2
            ],
            "x_size": 33,
            "x_descenders": 7,
            "x_ascenders": 9
          },
          "text": "Ashcroft\n      John,\n      stones,\n      40\n      John,\n      h\n      B’klyn"
        },
        {
          "properties": {
            "bbox": [
              1853,
              2779,
              2628,
              2814
            ],
            "baseline": [
              0,
              -2
            ],
            "x_size": 30,
            "x_descenders": 5,
            "x_ascenders": 9
          },
          "text": "Ashe\n      Frank,\n      carriages,\n      124\n      W.\n      35th,\n      h\n      163\n      Wilson,"
        },
        {
          "properties": {
            "bbox": [
              1919,
              2820,
              2018,
              2849
            ],
            "baseline": [
              0,
              -5
            ],
            "x_size": 31.865103,
            "x_descenders": 6.4791665,
            "x_ascenders": 8.6044779
          },
          "text": "Bklyn"
        },
        {
          "properties": {
            "bbox": [
              1853,
              2845,
              2389,
              2881
            ],
            "baseline": [
              0,
              -4
            ],
            "x_size": 32,
            "x_descenders": 6,
            "x_ascenders": 9
          },
          "text": "Ashe\n      Gregory,\n      grocer,\n      451\n      W.\n      19th"
        },
        {
          "properties": {
            "bbox": [
              1854,
              2879,
              2473,
              2914
            ],
            "baseline": [
              0,
              -4
            ],
            "x_size": 30,
            "x_descenders": 6,
            "x_ascenders": 7
          },
          "text": "Ashe\n      Mary\n      J.\n      wid.\n      Thomas,\n      b\n      425\n      Sixth"
        },
        {
          "properties": {
            "bbox": [
              1855,
              2912,
              2484,
              2946
            ],
            "baseline": [
              0,
              -3
            ],
            "x_size": 32,
            "x_descenders": 7,
            "x_ascenders": 9
          },
          "text": "Ashe\n      Matthew,\n      coachman,\n      h\n      329\n      E.\n      26th"
        },
        {
          "properties": {
            "bbox": [
              1857,
              2944,
              2633,
              2978
            ],
            "baseline": [
              0,
              -3
            ],
            "x_size": 32,
            "x_descenders": 7,
            "x_ascenders": 8
          },
          "text": "Ashe\n      William\n      F,\n      artist,\n      106\n      Bleecker,\n      h\n      Union\n      av."
        },
        {
          "properties": {
            "bbox": [
              1923,
              2984,
              2115,
              3007
            ],
            "baseline": [
              0,
              0
            ],
            "x_size": 30.503109,
            "x_descenders": 7.503109,
            "x_ascenders": 6
          },
          "text": "n\n      Boston\n      ay."
        },
        {
          "properties": {
            "bbox": [
              1859,
              3010,
              2493,
              3044
            ],
            "baseline": [
              0,
              -5
            ],
            "x_size": 33,
            "x_descenders": 7,
            "x_ascenders": 10
          },
          "text": "Ashead\n      Augustus\n      J,\n      packer,\n      h\n      737\n      E.\n      9th"
        },
        {
          "properties": {
            "bbox": [
              1860,
              3045,
              2274,
              3078
            ],
            "baseline": [
              0,
              -7
            ],
            "x_size": 33,
            "x_descenders": 8,
            "x_ascenders": 9
          },
          "text": "Asher\n      Aaron,\n      h\n      304\n      W.\n      33d"
        },
        {
          "properties": {
            "bbox": [
              1876,
              3109,
              2617,
              3148
            ],
            "baseline": [
              0,
              -6
            ],
            "x_size": 38.5,
            "x_descenders": 8.5,
            "x_ascenders": 6.5
          },
          "text": "FIRE\n      INS.\n      CO.,46\n      PINE\n      ST.,\n      Cor.\n      Wm."
        },
        {
          "properties": {
            "bbox": [
              2018,
              3143,
              2481,
              3181
            ],
            "baseline": [
              0,
              -7
            ],
            "x_size": 37,
            "x_descenders": 8,
            "x_ascenders": 6
          },
          "text": "Jas.\n      Yereance,\n      Manager,"
        }
      ],
      "columns": [
        991,
        1046
      ],
      "linesPerColumn": [
        43,
        37
      ],
      "minLinesPerColumn": false
    }
  ]
}