{
  "config": {
    "columnCount": 2,
    "characterWidth": 25,
    "minLinesPerColumn": 50
  },
  "pages": [
    {
      "number": 0,
      "properties": {
        "image": "saved.tif",
        "bbox": [
          0,
          0,
          2413,
          3557
        ],
        "ppageno": 0
      },
      "lines": [
        {
          "properties": {
            "bbox": [
              426,
              0,
              1821,
              24
            ],
            "baseline": [
              0,
              -34
            ],
            "x_size": 22.48064,
            "x_descenders": 3.4806409,
            "x_ascenders": 8
          },
          "text": "._\n      AN\n      ane\n      Wramd\n      deerme\n      wwe\n      a\n      AU\n      A\n      ULL"
        },
        {
          "properties": {
            "bbox": [
              350,
              0,
              1819,
              64
            ],
            "baseline": [
              0,
              -48
            ],
            "x_size": 38,
            "x_descenders": 7,
            "x_ascenders": 8
          },
          "text": "ay\n      mast\n      2atn\n      St.\n      (Union\n      Square),\n      Great\n      World’s\n      Exhibitions\n      for\n      13\n      years,"
        },
        {
          "properties": {
            "bbox": [
              539,
              49,
              1513,
              105
            ],
            "baseline": [
              0,
              -19
            ],
            "x_size": 49.833332,
            "x_descenders": 12.458333,
            "x_ascenders": 12.458333
          },
          "text": "DIE\n      379\n      DIE"
        },
        {
          "properties": {
            "bbox": [
              219,
              141,
              1732,
              194
            ],
            "baseline": [
              0,
              -29
            ],
            "x_size": 31,
            "x_descenders": 6,
            "x_ascenders": 8
          },
          "text": "Diercks\n      Catharine,\n      wid,\n      John\n      F,\n      h,\n      608\n      W.\n      45th\n      |\n      Dietrich\n      George,\n      baker,\n      h\n      r\n      252\n      E.\n      Houston",
          "columnIndex": 0,
          "completeText": "Diercks\n      Catharine,\n      wid,\n      John\n      F,\n      h,\n      608\n      W.\n      45th\n      |\n      Dietrich\n      George,\n      baker,\n      h\n      r\n      252\n      E.\n      Houston"
        },
        {
          "properties": {
            "bbox": [
              219,
              175,
              1708,
              228
            ],
            "baseline": [
              0,
              -30
            ],
            "x_size": 32,
            "x_descenders": 7,
            "x_ascenders": 8
          },
          "text": "Diercks\n      Frederick,\n      musician\n      h\n      272\n      E,\n      Houston\n      Dietrich\n      Henry,\n      clerk,\n      h\n      166th\n      n\n      R.\n      R.\n      av,",
          "columnIndex": 0,
          "completeText": "Diercks\n      Frederick,\n      musician\n      h\n      272\n      E,\n      Houston\n      Dietrich\n      Henry,\n      clerk,\n      h\n      166th\n      n\n      R.\n      R.\n      av,"
        },
        {
          "properties": {
            "bbox": [
              218,
              208,
              1600,
              258
            ],
            "baseline": [
              0,
              -26
            ],
            "x_size": 30,
            "x_descenders": 6,
            "x_ascenders": 7
          },
          "text": "Diercks\n      George.\n      agent,\n      h\n      6919\n      First\n      Dietrich\n      Henry,\n      cutter,\n      h\n      642\n      Sixth",
          "columnIndex": 0,
          "completeText": "Diercks\n      George.\n      agent,\n      h\n      6919\n      First\n      Dietrich\n      Henry,\n      cutter,\n      h\n      642\n      Sixth"
        },
        {
          "properties": {
            "bbox": [
              219,
              241,
              1615,
              292
            ],
            "baseline": [
              0,
              -27
            ],
            "x_size": 30,
            "x_descenders": 5,
            "x_ascenders": 8
          },
          "text": "Diercks\n      James\n      H.\n      bartender,\n      h\n      373\n      Bleecker\n      Dietrich\n      Henry,\n      eatingh.\n      110\n      W,\n      384",
          "columnIndex": 0,
          "completeText": "Diercks\n      James\n      H.\n      bartender,\n      h\n      373\n      Bleecker\n      Dietrich\n      Henry,\n      eatingh.\n      110\n      W,\n      384"
        },
        {
          "properties": {
            "bbox": [
              219,
              274,
              1699,
              326
            ],
            "baseline": [
              0,
              -28
            ],
            "x_size": 32,
            "x_descenders": 7,
            "x_ascenders": 8
          },
          "text": "Diercks\n      John,\n      smith,\n      107\n      Park\n      Dietrich\n      Henry,\n      shoemkr.\n      h\n      527\n      Ninth\n      av.",
          "columnIndex": 0,
          "completeText": "Diercks\n      John,\n      smith,\n      107\n      Park\n      Dietrich\n      Henry,\n      shoemkr.\n      h\n      527\n      Ninth\n      av."
        },
        {
          "properties": {
            "bbox": [
              218,
              307,
              1622,
              361
            ],
            "baseline": [
              0,
              -30
            ],
            "x_size": 31,
            "x_descenders": 7,
            "x_ascenders": 7
          },
          "text": "Diercks\n      John\n      H.\n      grocer,\n      690\n      Second\n      av.\n      .\n      Dietrich\n      John,\n      jeweler,\n      h\n      100\n      Second",
          "columnIndex": 0,
          "completeText": "Diercks\n      John\n      H.\n      grocer,\n      690\n      Second\n      av.\n      .\n      Dietrich\n      John,\n      jeweler,\n      h\n      100\n      Second"
        },
        {
          "properties": {
            "bbox": [
              219,
              341,
              1622,
              394
            ],
            "baseline": [
              0,
              -30
            ],
            "x_size": 31,
            "x_descenders": 6,
            "x_ascenders": 8
          },
          "text": "Diercks\n      Margaret\n      C.\n      wid.\n      John\n      H.\n      h\n      481\n      @’wich\n      Dietrich\n      John,\n      mason,\n      h\n      442\n      W,\n      49th",
          "columnIndex": 0,
          "completeText": "Diercks\n      Margaret\n      C.\n      wid.\n      John\n      H.\n      h\n      481\n      @’wich\n      Dietrich\n      John,\n      mason,\n      h\n      442\n      W,\n      49th"
        },
        {
          "properties": {
            "bbox": [
              218,
              374,
              1600,
              427
            ],
            "baseline": [
              0,
              -30
            ],
            "x_size": 31,
            "x_descenders": 6,
            "x_ascenders": 8
          },
          "text": "Diercksen\n      Carson,\n      eatingh.\n      319\n      West\n      Dietrich\n      John,\n      smith,\n      h\n      100\n      Second",
          "columnIndex": 0,
          "completeText": "Diercksen\n      Carson,\n      eatingh.\n      319\n      West\n      Dietrich\n      John,\n      smith,\n      h\n      100\n      Second"
        },
        {
          "properties": {
            "bbox": [
              218,
              407,
              1822,
              467
            ],
            "baseline": [
              0,
              -36
            ],
            "x_size": 31,
            "x_descenders": 6,
            "x_ascenders": 8
          },
          "text": "Dierckx\n      Peter\n      F,\n      eatingh.\n      45\n      Exchange\n      pl.\n      h\n      347\n      |\n      Dietrich\n      John\n      P,\n      meat,\n      352\n      Sixth\n      av.\n      h\n      5\n      Pacific\n      pl.",
          "columnIndex": 0,
          "completeText": "Dierckx\n      Peter\n      F,\n      eatingh.\n      45\n      Exchange\n      pl.\n      h\n      347\n      |\n      Dietrich\n      John\n      P,\n      meat,\n      352\n      Sixth\n      av.\n      h\n      5\n      Pacific\n      pl."
        },
        {
          "properties": {
            "bbox": [
              284,
              441,
              1824,
              496
            ],
            "baseline": [
              0,
              -31
            ],
            "x_size": 31,
            "x_descenders": 6,
            "x_ascenders": 8
          },
          "text": "W.\n      28th\n      Dietrich\n      Lewis,\n      framer,\n      135\n      Marion,\n      h\n      429\n      W,\n      56th"
        },
        {
          "properties": {
            "bbox": [
              217,
              473,
              1822,
              534
            ],
            "baseline": [
              0,
              -38
            ],
            "x_size": 33,
            "x_descenders": 7,
            "x_ascenders": 9
          },
          "text": "Dierckx\n      Pierre\n      F,\n      lawyer,\n      120\n      Bway,\n      h\n      £21\n      W,\n      28th\n      |\n      Dietrich\n      Louis,\n      engraver,\n      86\n      Maiden\n      la.\n      h\n      99414",
          "columnIndex": 0,
          "completeText": "Dierckx\n      Pierre\n      F,\n      lawyer,\n      120\n      Bway,\n      h\n      £21\n      W,\n      28th\n      |\n      Dietrich\n      Louis,\n      engraver,\n      86\n      Maiden\n      la.\n      h\n      99414"
        },
        {
          "properties": {
            "bbox": [
              217,
              507,
              1388,
              559
            ],
            "baseline": [
              0,
              -30
            ],
            "x_size": 32,
            "x_descenders": 7,
            "x_ascenders": 8
          },
          "text": "Dierig\n      Theodore,\n      sawdust,\n      h\n      201\n      S.\n      5th\n      av.\n      Greene\n      av,\n      B’klyn",
          "columnIndex": 0,
          "completeText": "Dierig\n      Theodore,\n      sawdust,\n      h\n      201\n      S.\n      5th\n      av.\n      Greene\n      av,\n      B’klyn"
        },
        {
          "properties": {
            "bbox": [
              216,
              539,
              1709,
              597
            ],
            "baseline": [
              0,
              -35
            ],
            "x_size": 32,
            "x_descenders": 7,
            "x_ascenders": 8
          },
          "text": "Diering\n      Henry\n      J.\n      supt.\n      h\n      Woodlawn\n      Dietrich\n      Louis,\n      upholsterer,\n      h\n      r\n      %3\n      Forsyth",
          "columnIndex": 0,
          "completeText": "Diering\n      Henry\n      J.\n      supt.\n      h\n      Woodlawn\n      Dietrich\n      Louis,\n      upholsterer,\n      h\n      r\n      %3\n      Forsyth"
        },
        {
          "properties": {
            "bbox": [
              216,
              573,
              1669,
              624
            ],
            "baseline": [
              0,
              -29
            ],
            "x_size": 30,
            "x_descenders": 6,
            "x_ascenders": 7
          },
          "text": "Dierkes\n      Frank,\n      basketmkr,\n      h\n      103\n      Norfolk\n      Dietrich\n      Louise,\n      wid,\n      John,\n      h\n      180\n      Av,\n      A",
          "columnIndex": 0,
          "completeText": "Dierkes\n      Frank,\n      basketmkr,\n      h\n      103\n      Norfolk\n      Dietrich\n      Louise,\n      wid,\n      John,\n      h\n      180\n      Av,\n      A"
        },
        {
          "properties": {
            "bbox": [
              217,
              606,
              1594,
              658
            ],
            "baseline": [
              0,
              -29
            ],
            "x_size": 31,
            "x_descenders": 6,
            "x_ascenders": 8
          },
          "text": "Dierkes\n      Hubert,\n      scalemkr.\n      h\n      334\n      W.\n      16th\n      Dietrich\n      Ludwig,\n      tailor,\n      h\n      6S\n      Av.\n      A",
          "columnIndex": 0,
          "completeText": "Dierkes\n      Hubert,\n      scalemkr.\n      h\n      334\n      W.\n      16th\n      Dietrich\n      Ludwig,\n      tailor,\n      h\n      6S\n      Av.\n      A"
        },
        {
          "properties": {
            "bbox": [
              215,
              639,
              1819,
              699
            ],
            "baseline": [
              0,
              -34
            ],
            "x_size": 32,
            "x_descenders": 6,
            "x_ascenders": 9
          },
          "text": "Dierkes\n      John,\n      laborer,\n      h\n      424\n      Fifth\n      Dietrich\n      Margaret,\n      wid.\n      Christian,\n      baskets,\n      50",
          "columnIndex": 0,
          "completeText": "Dierkes\n      John,\n      laborer,\n      h\n      424\n      Fifth\n      Dietrich\n      Margaret,\n      wid.\n      Christian,\n      baskets,\n      50"
        },
        {
          "properties": {
            "bbox": [
              215,
              672,
              1458,
              723
            ],
            "baseline": [
              0,
              -28
            ],
            "x_size": 33,
            "x_descenders": 8,
            "x_ascenders": 8
          },
          "text": "Dierkes\n      John\n      G.\n      carpenter,\n      h\n      124\n      Attorney\n      Maiden\n      la.\n      h\n      83\n      Henry",
          "columnIndex": 0,
          "completeText": "Dierkes\n      John\n      G.\n      carpenter,\n      h\n      124\n      Attorney\n      Maiden\n      la.\n      h\n      83\n      Henry"
        },
        {
          "properties": {
            "bbox": [
              215,
              705,
              1647,
              756
            ],
            "baseline": [
              0,
              -27
            ],
            "x_size": 32,
            "x_descenders": 7,
            "x_ascenders": 8
          },
          "text": "Dierking\n      Christian,\n      carpenter,\n      37\n      Forsyth\n      Dietrich\n      Max,\n      segarmkr,\n      h\n      r\n      161\n      Essex",
          "columnIndex": 0,
          "completeText": "Dierking\n      Christian,\n      carpenter,\n      37\n      Forsyth\n      Dietrich\n      Max,\n      segarmkr,\n      h\n      r\n      161\n      Essex"
        },
        {
          "properties": {
            "bbox": [
              213,
              738,
              1618,
              793
            ],
            "baseline": [
              0,
              -31
            ],
            "x_size": 30,
            "x_descenders": 6,
            "x_ascenders": 7
          },
          "text": "Dierks\n      Antonia,\n      wid.\n      Bernhard.\n      h\n      183\n      Orchard\n      Dietrich\n      Philip,\n      laborer,\n      h\n      71\n      Mangin",
          "columnIndex": 0,
          "completeText": "Dierks\n      Antonia,\n      wid.\n      Bernhard.\n      h\n      183\n      Orchard\n      Dietrich\n      Philip,\n      laborer,\n      h\n      71\n      Mangin"
        },
        {
          "properties": {
            "bbox": [
              212,
              771,
              1839,
              821
            ],
            "baseline": [
              0,
              -26
            ],
            "x_size": 28,
            "x_descenders": 4,
            "x_ascenders": 7
          },
          "text": "Dierks\n      Bernard\n      F,\n      seaman,\n      h\n      63\n      Monroe\n      Dietrich\n      Robert,\n      smith,\n      h\n      190\n      Clinton\n      .",
          "columnIndex": 0,
          "completeText": "Dierks\n      Bernard\n      F,\n      seaman,\n      h\n      63\n      Monroe\n      Dietrich\n      Robert,\n      smith,\n      h\n      190\n      Clinton\n      ."
        },
        {
          "properties": {
            "bbox": [
              212,
              804,
              1829,
              859
            ],
            "baseline": [
              0,
              -31
            ],
            "x_size": 34,
            "x_descenders": 9,
            "x_ascenders": 8
          },
          "text": "Dierks\n      John\n      H.\n      candy,\n      220)\n      Third\n      av.\n      h\n      2312\n      |\n      Dietrich\n      Wilhelmina,\n      wid.\n      Frederick,\n      h\n      r\n      184\n      Pitt,",
          "columnIndex": 0,
          "completeText": "Dierks\n      John\n      H.\n      candy,\n      220)\n      Third\n      av.\n      h\n      2312\n      |\n      Dietrich\n      Wilhelmina,\n      wid.\n      Frederick,\n      h\n      r\n      184\n      Pitt,"
        },
        {
          "properties": {
            "bbox": [
              278,
              839,
              1717,
              891
            ],
            "baseline": [
              0,
              -29
            ],
            "x_size": 32,
            "x_descenders": 7,
            "x_ascenders": 9
          },
          "text": "Third\n      av.\n      Dietrichsen\n      John\n      F.\n      teacher,\n      h\n      365\n      W.\n      36th"
        },
        {
          "properties": {
            "bbox": [
              211,
              871,
              1800,
              924
            ],
            "baseline": [
              0,
              -29
            ],
            "x_size": 35,
            "x_descenders": 5,
            "x_ascenders": 13
          },
          "text": "Dierks\n      Rudolph,\n      grocer,\n      60\n      Bedford,\n      h\n      29\n      Morton\n      |\n      Dietrichssen\n      William,\n      photographer,\n      h\n      29\n      Second",
          "columnIndex": 0,
          "completeText": "Dierks\n      Rudolph,\n      grocer,\n      60\n      Bedford,\n      h\n      29\n      Morton\n      |\n      Dietrichssen\n      William,\n      photographer,\n      h\n      29\n      Second"
        },
        {
          "properties": {
            "bbox": [
              210,
              904,
              1702,
              955
            ],
            "baseline": [
              0,
              -27
            ],
            "x_size": 31,
            "x_descenders": 6,
            "x_ascenders": 8
          },
          "text": "Diers\n      Albert,\n      segars,\n      h\n      144\n      E,\n      19th\n      Dietrichstein\n      Maurice,\n      clerk,\n      h\n      312\n      E.\n      21st",
          "columnIndex": 0,
          "completeText": "Diers\n      Albert,\n      segars,\n      h\n      144\n      E,\n      19th\n      Dietrichstein\n      Maurice,\n      clerk,\n      h\n      312\n      E.\n      21st"
        },
        {
          "properties": {
            "bbox": [
              209,
              938,
              1814,
              991
            ],
            "baseline": [
              0,
              -31
            ],
            "x_size": 30,
            "x_descenders": 6,
            "x_ascenders": 7
          },
          "text": "Diers\n      John,\n      laborer,\n      h\n      89\n      Montgomery\n      Dietsch\n      Morris,\n      dispensary,\n      Westchester\n      av.\n      n",
          "columnIndex": 0,
          "completeText": "Diers\n      John,\n      laborer,\n      h\n      89\n      Montgomery\n      Dietsch\n      Morris,\n      dispensary,\n      Westchester\n      av.\n      n"
        },
        {
          "properties": {
            "bbox": [
              209,
              971,
              1530,
              1017
            ],
            "baseline": [
              0,
              -24
            ],
            "x_size": 33,
            "x_descenders": 4,
            "x_ascenders": 12
          },
          "text": "Diersen\n      Mary,\n      wid.\n      Hyman.\n      h\n      W.\n      160th\n      ¢\n      Ninthay.\n      Brook,\n      h\n      149th\n      ¢\n      Boulevard",
          "columnIndex": 0,
          "completeText": "Diersen\n      Mary,\n      wid.\n      Hyman.\n      h\n      W.\n      160th\n      ¢\n      Ninthay.\n      Brook,\n      h\n      149th\n      ¢\n      Boulevard"
        },
        {
          "properties": {
            "bbox": [
              208,
              1004,
              1650,
              1052
            ],
            "baseline": [
              0,
              -25
            ],
            "x_size": 32,
            "x_descenders": 7,
            "x_ascenders": 8
          },
          "text": "Diertch\n      John,\n      laborer,\n      h\n      7\n      Hester\n      Diettman\n      Francis,\n      smith,\n      h\n      137\n      Ludlow",
          "columnIndex": 0,
          "completeText": "Diertch\n      John,\n      laborer,\n      h\n      7\n      Hester\n      Diettman\n      Francis,\n      smith,\n      h\n      137\n      Ludlow"
        },
        {
          "properties": {
            "bbox": [
              207,
              1037,
              1550,
              1086
            ],
            "baseline": [
              0,
              -26
            ],
            "x_size": 31,
            "x_descenders": 7,
            "x_ascenders": 7
          },
          "text": "Dies\n      Andrew,\n      mason,\n      h\n      131\n      Ridge\n      Dietz\n      Adam,\n      stationer,\n      475\n      Canal",
          "columnIndex": 0,
          "completeText": "Dies\n      Andrew,\n      mason,\n      h\n      131\n      Ridge\n      Dietz\n      Adam,\n      stationer,\n      475\n      Canal"
        },
        {
          "properties": {
            "bbox": [
              207,
              1070,
              1629,
              1121
            ],
            "baseline": [
              0,
              -27
            ],
            "x_size": 32,
            "x_descenders": 8,
            "x_ascenders": 7
          },
          "text": "Dies\n      Max,\n      laborer,\n      h\n      170\n      Etm\n      Dietz\n      Alfred\n      J.\n      clerk,\n      h\n      197\n      Second\n      ay.",
          "columnIndex": 0,
          "completeText": "Dies\n      Max,\n      laborer,\n      h\n      170\n      Etm\n      Dietz\n      Alfred\n      J.\n      clerk,\n      h\n      197\n      Second\n      ay."
        },
        {
          "properties": {
            "bbox": [
              206,
              1104,
              1716,
              1155
            ],
            "baseline": [
              0,
              -30
            ],
            "x_size": 31,
            "x_descenders": 6,
            "x_ascenders": 8
          },
          "text": "Dies\n      Paul,\n      scavenger,\n      h\n      r\n      207\n      Av.\n      B\n      Dietz\n      Barbara,\n      wid.\n      Clements,\n      h\n      407\n      E.\n      14th",
          "columnIndex": 0,
          "completeText": "Dies\n      Paul,\n      scavenger,\n      h\n      r\n      207\n      Av.\n      B\n      Dietz\n      Barbara,\n      wid.\n      Clements,\n      h\n      407\n      E.\n      14th"
        },
        {
          "properties": {
            "bbox": [
              206,
              1137,
              1705,
              1188
            ],
            "baseline": [
              0,
              -30
            ],
            "x_size": 31,
            "x_descenders": 6,
            "x_ascenders": 8
          },
          "text": "Dies\n      Ralph,\n      segarmkr,\n      h\n      5\n      Chrystie\n      Dietz\n      Catharine,\n      wid.\n      Henry,\n      h\n      214\n      E.\n      20th",
          "columnIndex": 0,
          "completeText": "Dies\n      Ralph,\n      segarmkr,\n      h\n      5\n      Chrystie\n      Dietz\n      Catharine,\n      wid.\n      Henry,\n      h\n      214\n      E.\n      20th"
        },
        {
          "properties": {
            "bbox": [
              206,
              1170,
              1570,
              1216
            ],
            "baseline": [
              0,
              -24
            ],
            "x_size": 36,
            "x_descenders": 8,
            "x_ascenders": 12
          },
          "text": "Diescher\n      Ferdinand,\n      clerk,\n      h\n      328\n      BE.\n      9th\n      Dietz\n      Charles,\n      laborer,\n      h\n      131\n      Third",
          "columnIndex": 0,
          "completeText": "Diescher\n      Ferdinand,\n      clerk,\n      h\n      328\n      BE.\n      9th\n      Dietz\n      Charles,\n      laborer,\n      h\n      131\n      Third"
        },
        {
          "properties": {
            "bbox": [
              205,
              1203,
              1614,
              1250
            ],
            "baseline": [
              0,
              -24
            ],
            "x_size": 37.554962,
            "x_descenders": 8.5549631,
            "x_ascenders": 7
          },
          "text": "Diescher\n      George\n      H.\n      tailor,\n      530\n      Second\n      av.\n      Dietz\n      Charles,\n      papermkr.\n      h\n      114\n      Essex",
          "columnIndex": 0,
          "completeText": "Diescher\n      George\n      H.\n      tailor,\n      530\n      Second\n      av.\n      Dietz\n      Charles,\n      papermkr.\n      h\n      114\n      Essex"
        },
        {
          "properties": {
            "bbox": [
              206,
              1236,
              1805,
              1289
            ],
            "baseline": [
              0,
              -29
            ],
            "x_size": 31,
            "x_descenders": 6,
            "x_ascenders": 8
          },
          "text": "Diesel\n      William,\n      brushmkr.\n      311\n      E.\n      45th\n      Dietz\n      Charles,\n      pianos,\n      219\n      E.\n      23d,\n      h\n      385\n      Second\n      ay.",
          "columnIndex": 0,
          "completeText": "Diesel\n      William,\n      brushmkr.\n      311\n      E.\n      45th\n      Dietz\n      Charles,\n      pianos,\n      219\n      E.\n      23d,\n      h\n      385\n      Second\n      ay."
        },
        {
          "properties": {
            "bbox": [
              203,
              1269,
              1535,
              1321
            ],
            "baseline": [
              0,
              -29
            ],
            "x_size": 35,
            "x_descenders": 5,
            "x_ascenders": 13
          },
          "text": "Dieselswager\n      Adam,\n      brewer,\n      h\n      Cauldwell\n      av.\n      n\n      (see\n      adv.\n      page\n      62,\n      com.\n      reg.)",
          "columnIndex": 0,
          "completeText": "Dieselswager\n      Adam,\n      brewer,\n      h\n      Cauldwell\n      av.\n      n\n      (see\n      adv.\n      page\n      62,\n      com.\n      reg.)"
        },
        {
          "properties": {
            "bbox": [
              271,
              1303,
              1804,
              1355
            ],
            "baseline": [
              0,
              -27
            ],
            "x_size": 31,
            "x_descenders": 6,
            "x_ascenders": 8
          },
          "text": "Cedar\n      Dietz\n      Chas.\n      H.\n      meat,\n      555\n      Third\n      av,\n      h\n      554\n      Thirday,"
        },
        {
          "properties": {
            "bbox": [
              203,
              1335,
              1534,
              1386
            ],
            "baseline": [
              0,
              -27
            ],
            "x_size": 35,
            "x_descenders": 9,
            "x_ascenders": 9
          },
          "text": "Diesend\n      Emil,\n      h\n      508\n      W.\n      43a\n      Dietz\n      Conrad,\n      painter,\n      187\n      Av.\n      A",
          "columnIndex": 0,
          "completeText": "Diesend\n      Emil,\n      h\n      508\n      W.\n      43a\n      Dietz\n      Conrad,\n      painter,\n      187\n      Av.\n      A"
        },
        {
          "properties": {
            "bbox": [
              201,
              1369,
              2226,
              1415
            ],
            "baseline": [
              0,
              -23
            ],
            "x_size": 28,
            "x_descenders": 4,
            "x_ascenders": 8
          },
          "text": "Diessle\n      Charles,\n      porter,\n      h\n      220\n      Seventh\n      Dietz\n      Conrad,\n      tailor,\n      h\n      20\n      Stanton\n      ‘",
          "columnIndex": 0,
          "completeText": "Diessle\n      Charles,\n      porter,\n      h\n      220\n      Seventh\n      Dietz\n      Conrad,\n      tailor,\n      h\n      20\n      Stanton\n      ‘"
        },
        {
          "properties": {
            "bbox": [
              2226,
              1456,
              2239,
              1499
            ],
            "baseline": [
              0,
              0
            ],
            "x_size": 54.27195,
            "x_descenders": 11.27195,
            "x_ascenders": 14.012978
          },
          "text": "4"
        },
        {
          "properties": {
            "bbox": [
              201,
              1402,
              1628,
              1451
            ],
            "baseline": [
              0,
              -26
            ],
            "x_size": 33,
            "x_descenders": 8,
            "x_ascenders": 8
          },
          "text": "Diestel\n      Andrew,\n      laborer,\n      h\n      6\n      Mott's\n      la,\n      Dietz\n      Daniel,\n      cartman,\n      hr\n      231\n      W.\n      3%th",
          "columnIndex": 0,
          "completeText": "Diestel\n      Andrew,\n      laborer,\n      h\n      6\n      Mott's\n      la,\n      Dietz\n      Daniel,\n      cartman,\n      hr\n      231\n      W.\n      3%th"
        },
        {
          "properties": {
            "bbox": [
              201,
              1435,
              1804,
              1490
            ],
            "baseline": [
              0,
              -32
            ],
            "x_size": 32,
            "x_descenders": 7,
            "x_ascenders": 8
          },
          "text": "Diestel\n      Ferdinand,\n      cabinetmkr.\n      h\n      648\n      Fifth\n      Dietz\n      Dorothea,\n      wid.\n      George,\n      milk,\n      329\n      Rivington,",
          "columnIndex": 0,
          "completeText": "Diestel\n      Ferdinand,\n      cabinetmkr.\n      h\n      648\n      Fifth\n      Dietz\n      Dorothea,\n      wid.\n      George,\n      milk,\n      329\n      Rivington,"
        },
        {
          "properties": {
            "bbox": [
              200,
              1468,
              1518,
              1515
            ],
            "baseline": [
              0,
              -23
            ],
            "x_size": 30,
            "x_descenders": 6,
            "x_ascenders": 7
          },
          "text": "Diestel\n      George,\n      porter,\n      h\n      439\n      Sixth\n      Dietz\n      Frank,\n      meat,\n      521\n      W.\n      40th",
          "columnIndex": 0,
          "completeText": "Diestel\n      George,\n      porter,\n      h\n      439\n      Sixth\n      Dietz\n      Frank,\n      meat,\n      521\n      W.\n      40th"
        },
        {
          "properties": {
            "bbox": [
              199,
              1487,
              2256,
              1566
            ],
            "baseline": [
              0,
              -41
            ],
            "x_size": 29,
            "x_descenders": 5,
            "x_ascenders": 7
          },
          "text": "Diestell\n      Andrew,\n      Iaborer,\n      h\n      614\n      W.\n      5\n      {th\n      Dietz\n      Franz,\n      beer,\n      527\n      First\n      av.\n      {\n      \\\n      |\n      f",
          "columnIndex": 0,
          "completeText": "Diestell\n      Andrew,\n      Iaborer,\n      h\n      614\n      W.\n      5\n      {th\n      Dietz\n      Franz,\n      beer,\n      527\n      First\n      av.\n      {\n      \\\n      |\n      f"
        },
        {
          "properties": {
            "bbox": [
              200,
              1535,
              2238,
              1601
            ],
            "baseline": [
              0,
              -43
            ],
            "x_size": 34,
            "x_descenders": 8,
            "x_ascenders": 10
          },
          "text": "Diestle\n      Julia,\n      wid.\n      Charles,\n      h\n      808\n      Henry\n      Dietz\n      Frederick,\n      barber,\n      200\n      E.\n      46th,\n      h\n      231\n      E.\n      46th\n      no\n      i",
          "columnIndex": 0,
          "completeText": "Diestle\n      Julia,\n      wid.\n      Charles,\n      h\n      808\n      Henry\n      Dietz\n      Frederick,\n      barber,\n      200\n      E.\n      46th,\n      h\n      231\n      E.\n      46th\n      no\n      i"
        },
        {
          "properties": {
            "bbox": [
              198,
              1568,
              2205,
              1616
            ],
            "baseline": [
              0,
              -25
            ],
            "x_size": 30,
            "x_descenders": 6,
            "x_ascenders": 7
          },
          "text": "Diestler\n      1dam,\n      painter,\n      h\n      185\n      Third\n      Dietz\n      Frederick,\n      lithographer.\n      h\n      307\n      E.\n      T4th\n      re",
          "columnIndex": 0,
          "completeText": "Diestler\n      1dam,\n      painter,\n      h\n      185\n      Third\n      Dietz\n      Frederick,\n      lithographer.\n      h\n      307\n      E.\n      T4th\n      re"
        },
        {
          "properties": {
            "bbox": [
              198,
              1601,
              2262,
              1673
            ],
            "baseline": [
              0,
              -49
            ],
            "x_size": 32,
            "x_descenders": 7,
            "x_ascenders": 8
          },
          "text": "Dietch\n      Conrad,\n      laborer,\n      h\n      r\n      61\n      Sheriff\n      Dietz\n      Frederick,\n      musician,\n      h\n      %6\n      E.\n      4th\n      :\n      ri",
          "columnIndex": 0,
          "completeText": "Dietch\n      Conrad,\n      laborer,\n      h\n      r\n      61\n      Sheriff\n      Dietz\n      Frederick,\n      musician,\n      h\n      %6\n      E.\n      4th\n      :\n      ri"
        },
        {
          "properties": {
            "bbox": [
              199,
              1634,
              2289,
              1699
            ],
            "baseline": [
              0,
              -42
            ],
            "x_size": 44,
            "x_descenders": 7,
            "x_ascenders": 13
          },
          "text": "Dietch\n      Henry,\n      hatter,\n      h\n      89\n      Norfolk\n      Dietz\n      Frederick,\n      pianomkr.\n      h\n      510\n      W.\n      4th\n      .\n      plc?",
          "columnIndex": 0,
          "completeText": "Dietch\n      Henry,\n      hatter,\n      h\n      89\n      Norfolk\n      Dietz\n      Frederick,\n      pianomkr.\n      h\n      510\n      W.\n      4th\n      .\n      plc?"
        },
        {
          "properties": {
            "bbox": [
              196,
              1667,
              2236,
              1743
            ],
            "baseline": [
              0,
              -53
            ],
            "x_size": 33,
            "x_descenders": 9,
            "x_ascenders": 7
          },
          "text": "Dietch\n      Samuel,\n      laborer,\n      h\n      128\n      Ludlow\n      Dietz\n      Frederick,\n      varnisher,\n      h\n      260\n      Third\n      {",
          "columnIndex": 0,
          "completeText": "Dietch\n      Samuel,\n      laborer,\n      h\n      128\n      Ludlow\n      Dietz\n      Frederick,\n      varnisher,\n      h\n      260\n      Third\n      {"
        },
        {
          "properties": {
            "bbox": [
              195,
              1700,
              2182,
              1752
            ],
            "baseline": [
              0,
              -29
            ],
            "x_size": 29,
            "x_descenders": 5,
            "x_ascenders": 7
          },
          "text": "Dietcher\n      Leopold,\n      turner,\n      h\n      r\n      169\n      Siffolk\n      Dietz\n      Frederick\n      G.\n      h64\n      Elm\n      f\n      ‘",
          "columnIndex": 0,
          "completeText": "Dietcher\n      Leopold,\n      turner,\n      h\n      r\n      169\n      Siffolk\n      Dietz\n      Frederick\n      G.\n      h64\n      Elm\n      f\n      ‘"
        },
        {
          "properties": {
            "bbox": [
              196,
              1733,
              978,
              1774
            ],
            "baseline": [
              0,
              -18
            ],
            "x_size": 30,
            "x_descenders": 6,
            "x_ascenders": 7
          },
          "text": "Dietenbach\n      Joseph,\n      cabinetmkr.\n      h\n      875\n      Second\n      av,",
          "columnIndex": 0,
          "completeText": "Dietenbach\n      Joseph,\n      cabinetmkr.\n      h\n      875\n      Second\n      av,"
        },
        {
          "properties": {
            "bbox": [
              195,
              1767,
              736,
              1801
            ],
            "baseline": [
              0,
              -11
            ],
            "x_size": 29,
            "x_descenders": 5,
            "x_ascenders": 7
          },
          "text": "Dieter\n      Arthur,\n      painter,\n      h\n      60\n      E.\n      4th",
          "columnIndex": 0,
          "completeText": "Dieter\n      Arthur,\n      painter,\n      h\n      60\n      E.\n      4th"
        },
        {
          "properties": {
            "bbox": [
              194,
              1800,
              738,
              1835
            ],
            "baseline": [
              0,
              -13
            ],
            "x_size": 30,
            "x_descenders": 6,
            "x_ascenders": 7
          },
          "text": "Dieter\n      Conrad,\n      smith,\n      112\n      Stanton",
          "columnIndex": 0,
          "completeText": "Dieter\n      Conrad,\n      smith,\n      112\n      Stanton"
        },
        {
          "properties": {
            "bbox": [
              193,
              1832,
              815,
              1870
            ],
            "baseline": [
              0,
              -15
            ],
            "x_size": 32,
            "x_descenders": 7,
            "x_ascenders": 8
          },
          "text": "Dieter\n      Frederick\n      K.\n      artist,\n      h\n      315\n      E.\n      21st",
          "columnIndex": 1,
          "completeText": "Dieter\n      Frederick\n      K.\n      artist,\n      h\n      315\n      E.\n      21st"
        },
        {
          "properties": {
            "bbox": [
              192,
              1866,
              911,
              1905
            ],
            "baseline": [
              0,
              -17
            ],
            "x_size": 31,
            "x_descenders": 7,
            "x_ascenders": 7
          },
          "text": "Dieter\n      Jacob,\n      cabinetmkr.\n      3\n      First,\n      h\n      415\n      Fifth",
          "columnIndex": 1,
          "completeText": "Dieter\n      Jacob,\n      cabinetmkr.\n      3\n      First,\n      h\n      415\n      Fifth"
        },
        {
          "properties": {
            "bbox": [
              193,
              1899,
              798,
              1937
            ],
            "baseline": [
              0,
              -15
            ],
            "x_size": 31,
            "x_descenders": 6,
            "x_ascenders": 9
          },
          "text": "Dieter\n      Jacob,\n      sawyer,\n      h\n      143\n      Thompson",
          "columnIndex": 1,
          "completeText": "Dieter\n      Jacob,\n      sawyer,\n      h\n      143\n      Thompson"
        },
        {
          "properties": {
            "bbox": [
              191,
              1932,
              730,
              1967
            ],
            "baseline": [
              0,
              -12
            ],
            "x_size": 28,
            "x_descenders": 4,
            "x_ascenders": 7
          },
          "text": "Dieter\n      John,\n      baker,\n      h\n      r\n      89\n      Clinton",
          "columnIndex": 1,
          "completeText": "Dieter\n      John,\n      baker,\n      h\n      r\n      89\n      Clinton"
        },
        {
          "properties": {
            "bbox": [
              189,
              1965,
              813,
              2001
            ],
            "baseline": [
              0,
              -13
            ],
            "x_size": 30,
            "x_descenders": 6,
            "x_ascenders": 7
          },
          "text": "Dieter\n      Martin,\n      carpenter,\n      h\n      114\n      Stanton",
          "columnIndex": 1,
          "completeText": "Dieter\n      Martin,\n      carpenter,\n      h\n      114\n      Stanton"
        },
        {
          "properties": {
            "bbox": [
              191,
              1999,
              730,
              2033
            ],
            "baseline": [
              0,
              -11
            ],
            "x_size": 31,
            "x_descenders": 7,
            "x_ascenders": 7
          },
          "text": "Dieter\n      Paul,\n      shoes,\n      456\n      Fourth\n      av.",
          "columnIndex": 1,
          "completeText": "Dieter\n      Paul,\n      shoes,\n      456\n      Fourth\n      av."
        },
        {
          "properties": {
            "bbox": [
              189,
              2032,
              858,
              2068
            ],
            "baseline": [
              0,
              -13
            ],
            "x_size": 29,
            "x_descenders": 4,
            "x_ascenders": 8
          },
          "text": "Dieterich\n      Anthony,\n      beer,\n      784\n      Eleventh\n      av.",
          "columnIndex": 1,
          "completeText": "Dieterich\n      Anthony,\n      beer,\n      784\n      Eleventh\n      av."
        },
        {
          "properties": {
            "bbox": [
              189,
              2065,
              850,
              2101
            ],
            "baseline": [
              0,
              -13
            ],
            "x_size": 30,
            "x_descenders": 6,
            "x_ascenders": 7
          },
          "text": "Dieterich\n      August\n      W.\n      drugs,\n      756\n      Tenth\n      av.",
          "columnIndex": 1,
          "completeText": "Dieterich\n      August\n      W.\n      drugs,\n      756\n      Tenth\n      av."
        },
        {
          "properties": {
            "bbox": [
              188,
              2098,
              861,
              2133
            ],
            "baseline": [
              0,
              -12
            ],
            "x_size": 31,
            "x_descenders": 6,
            "x_ascenders": 8
          },
          "text": "Dieterich\n      Charles,\n      uppers,\n      119\n      W.\n      Houston",
          "columnIndex": 1,
          "completeText": "Dieterich\n      Charles,\n      uppers,\n      119\n      W.\n      Houston"
        },
        {
          "properties": {
            "bbox": [
              187,
              2129,
              688,
              2169
            ],
            "baseline": [
              0,
              -14
            ],
            "x_size": 34,
            "x_descenders": 7,
            "x_ascenders": 11
          },
          "text": "Dieterich\n      Edward\n      F.\n      h\n      25\n      Perry",
          "columnIndex": 1,
          "completeText": "Dieterich\n      Edward\n      F.\n      h\n      25\n      Perry"
        },
        {
          "properties": {
            "bbox": [
              186,
              2165,
              943,
              2203
            ],
            "baseline": [
              0,
              -15
            ],
            "x_size": 33,
            "x_descenders": 8,
            "x_ascenders": 8
          },
          "text": "Dieterich\n      Frank.\n      barber,\n      28\n      New,\n      h\n      180\n      Seventh",
          "columnIndex": 1,
          "completeText": "Dieterich\n      Frank.\n      barber,\n      28\n      New,\n      h\n      180\n      Seventh"
        },
        {
          "properties": {
            "bbox": [
              187,
              2198,
              895,
              2237
            ],
            "baseline": [
              0,
              -16
            ],
            "x_size": 30,
            "x_descenders": 6,
            "x_ascenders": 8
          },
          "text": "Dieterich\n      George,\n      varnisher,\n      h\n      r\n      47\n      Eldridge",
          "columnIndex": 1,
          "completeText": "Dieterich\n      George,\n      varnisher,\n      h\n      r\n      47\n      Eldridge"
        },
        {
          "properties": {
            "bbox": [
              185,
              2230,
              840,
              2265
            ],
            "baseline": [
              0,
              -10
            ],
            "x_size": 31,
            "x_descenders": 6,
            "x_ascenders": 8
          },
          "text": "Dieterich\n      Gustav,\n      artist,\n      h\n      100\n      Second\n      av,",
          "columnIndex": 1,
          "completeText": "Dieterich\n      Gustav,\n      artist,\n      h\n      100\n      Second\n      av,"
        },
        {
          "properties": {
            "bbox": [
              186,
              2264,
              795,
              2298
            ],
            "baseline": [
              0,
              -11
            ],
            "x_size": 31,
            "x_descenders": 6,
            "x_ascenders": 8
          },
          "text": "Dieterich\n      Louis,\n      waiter,\n      h\n      127\n      First\n      av.",
          "columnIndex": 1,
          "completeText": "Dieterich\n      Louis,\n      waiter,\n      h\n      127\n      First\n      av."
        },
        {
          "properties": {
            "bbox": [
              184,
              2297,
              886,
              2334
            ],
            "baseline": [
              0,
              -14
            ],
            "x_size": 31,
            "x_descenders": 6,
            "x_ascenders": 9
          },
          "text": "Dieterle\n      Frederick,\n      fixtures,\n      h\n      51434\n      W.\n      26th",
          "columnIndex": 1,
          "completeText": "Dieterle\n      Frederick,\n      fixtures,\n      h\n      51434\n      W.\n      26th"
        },
        {
          "properties": {
            "bbox": [
              184,
              2330,
              755,
              2365
            ],
            "baseline": [
              0,
              -12
            ],
            "x_size": 32,
            "x_descenders": 7,
            "x_ascenders": 8
          },
          "text": "Dieterle\n      Hector,\n      cutter,\n      h\n      166\n      B.\n      4th",
          "columnIndex": 1,
          "completeText": "Dieterle\n      Hector,\n      cutter,\n      h\n      166\n      B.\n      4th"
        },
        {
          "properties": {
            "bbox": [
              183,
              2364,
              968,
              2405
            ],
            "baseline": [
              0,
              -19
            ],
            "x_size": 33,
            "x_descenders": 8,
            "x_ascenders": 8
          },
          "text": "Dieterlen\n      Theodore,\n      carpenter,\n      122\n      E.\n      129th,\n      h\n      41",
          "columnIndex": 1,
          "completeText": "Dieterlen\n      Theodore,\n      carpenter,\n      122\n      E.\n      129th,\n      h\n      41"
        },
        {
          "properties": {
            "bbox": [
              248,
              2397,
              386,
              2423
            ],
            "baseline": [
              0,
              -2
            ],
            "x_size": 32.48156,
            "x_descenders": 6.7686567,
            "x_ascenders": 8.323741
          },
          "text": "W.\n      127th"
        },
        {
          "properties": {
            "bbox": [
              182,
              2430,
              889,
              2466
            ],
            "baseline": [
              0,
              -13
            ],
            "x_size": 32,
            "x_descenders": 7,
            "x_ascenders": 8
          },
          "text": "Dieterlen\n      William,\n      brewer,\n      h\n      1074\n      Second\n      ay,",
          "columnIndex": 1,
          "completeText": "Dieterlen\n      William,\n      brewer,\n      h\n      1074\n      Second\n      ay,"
        },
        {
          "properties": {
            "bbox": [
              181,
              2463,
              821,
              2496
            ],
            "baseline": [
              0,
              -10
            ],
            "x_size": 31,
            "x_descenders": 6,
            "x_ascenders": 8
          },
          "text": "Dietmann\n      Leopold,\n      cutter,\n      h\n      100\n      Clinton",
          "columnIndex": 1,
          "completeText": "Dietmann\n      Leopold,\n      cutter,\n      h\n      100\n      Clinton"
        },
        {
          "properties": {
            "bbox": [
              182,
              2496,
              943,
              2534
            ],
            "baseline": [
              0,
              -15
            ],
            "x_size": 33,
            "x_descenders": 8,
            "x_ascenders": 8
          },
          "text": "Dietrich\n      Adam,\n      barber,\n      1936\n      B'way,\n      h\n      201\n      Av.\n      A",
          "columnIndex": 1,
          "completeText": "Dietrich\n      Adam,\n      barber,\n      1936\n      B'way,\n      h\n      201\n      Av.\n      A"
        },
        {
          "properties": {
            "bbox": [
              180,
              2529,
              968,
              2570
            ],
            "baseline": [
              0,
              -18
            ],
            "x_size": 31,
            "x_descenders": 6,
            "x_ascenders": 8
          },
          "text": "Dietrich\n      Adam,\n      painter,\n      148\n      Eldridge,\n      h\n      67\n      Delancey",
          "columnIndex": 1,
          "completeText": "Dietrich\n      Adam,\n      painter,\n      148\n      Eldridge,\n      h\n      67\n      Delancey"
        },
        {
          "properties": {
            "bbox": [
              182,
              2563,
              939,
              2603
            ],
            "baseline": [
              0,
              -17
            ],
            "x_size": 33,
            "x_descenders": 8,
            "x_ascenders": 8
          },
          "text": "Dietrich\n      Adam,\n      whalebone,\n      86\n      Walker,\n      h\n      B'klyn",
          "columnIndex": 1,
          "completeText": "Dietrich\n      Adam,\n      whalebone,\n      86\n      Walker,\n      h\n      B'klyn"
        },
        {
          "properties": {
            "bbox": [
              179,
              2596,
              726,
              2628
            ],
            "baseline": [
              0,
              -9
            ],
            "x_size": 31,
            "x_descenders": 6,
            "x_ascenders": 8
          },
          "text": "Dietrich\n      Adolph,\n      agent,\n      h69\n      Third",
          "columnIndex": 1,
          "completeText": "Dietrich\n      Adolph,\n      agent,\n      h69\n      Third"
        },
        {
          "properties": {
            "bbox": [
              179,
              2628,
              901,
              2665
            ],
            "baseline": [
              0,
              -13
            ],
            "x_size": 31,
            "x_descenders": 7,
            "x_ascenders": 7
          },
          "text": "Dietrich\n      Apollonia,\n      wid,\n      Charles,\n      h\n      250\n      E.\n      4th",
          "columnIndex": 1,
          "completeText": "Dietrich\n      Apollonia,\n      wid,\n      Charles,\n      h\n      250\n      E.\n      4th"
        },
        {
          "properties": {
            "bbox": [
              1016,
              1741,
              2258,
              1796
            ],
            "baseline": [
              0,
              -28
            ],
            "x_size": 29,
            "x_descenders": 4,
            "x_ascenders": 8
          },
          "text": "Dietz\n      George,\n      h\n      74\n      Cannon\n      é"
        },
        {
          "properties": {
            "bbox": [
              1015,
              1779,
              2267,
              1860
            ],
            "baseline": [
              0,
              -58
            ],
            "x_size": 30,
            "x_descenders": 6,
            "x_ascenders": 8
          },
          "text": "Dietz\n      George,\n      h\n      319\n      Rivington\n      /"
        },
        {
          "properties": {
            "bbox": [
              1015,
              1812,
              1825,
              1850
            ],
            "baseline": [
              0,
              -15
            ],
            "x_size": 31,
            "x_descenders": 6,
            "x_ascenders": 9
          },
          "text": "Dietz\n      George,\n      clerk,\n      h\n      203\n      Rivington\n      -"
        },
        {
          "properties": {
            "bbox": [
              1014,
              1844,
              2237,
              1891
            ],
            "baseline": [
              0,
              -23
            ],
            "x_size": 30,
            "x_descenders": 6,
            "x_ascenders": 8
          },
          "text": "Dietz\n      George,\n      grocer,\n      169th\n      n\n      Third\n      av.\n      |"
        },
        {
          "properties": {
            "bbox": [
              1014,
              1877,
              2273,
              1936
            ],
            "baseline": [
              0,
              -35
            ],
            "x_size": 31,
            "x_descenders": 6,
            "x_ascenders": 9
          },
          "text": "Dietz\n      George,\n      mason,\n      h\n      369\n      E.\n      T6th\n      ‘\n      f\n      ‘"
        },
        {
          "properties": {
            "bbox": [
              1013,
              1910,
              2237,
              1952
            ],
            "baseline": [
              0,
              -18
            ],
            "x_size": 34,
            "x_descenders": 6,
            "x_ascenders": 11
          },
          "text": "Dietz\n      George,\n      toys,\n      r\n      234\n      Broome"
        },
        {
          "properties": {
            "bbox": [
              1011,
              1944,
              2274,
              2013
            ],
            "baseline": [
              0,
              -46
            ],
            "x_size": 37,
            "x_descenders": 7,
            "x_ascenders": 7
          },
          "text": "Dietz\n      Henry,\n      milk,\n      148\n      Av.\n      C\n      i\n      /"
        },
        {
          "properties": {
            "bbox": [
              1011,
              1976,
              2236,
              2015
            ],
            "baseline": [
              0,
              -15
            ],
            "x_size": 33,
            "x_descenders": 7,
            "x_ascenders": 10
          },
          "text": "Dietz\n      Henry\n      M.\n      taiior,\n      1641\n      Third\n      ay.\n      ‘\n      '"
        },
        {
          "properties": {
            "bbox": [
              1010,
              2009,
              2251,
              2044
            ],
            "baseline": [
              0,
              -12
            ],
            "x_size": 32,
            "x_descenders": 7,
            "x_ascenders": 8
          },
          "text": "Dietz\n      Isidor,\n      notions,\n      1314\n      Third\n      ay."
        },
        {
          "properties": {
            "bbox": [
              1010,
              2042,
              2278,
              2103
            ],
            "baseline": [
              0,
              -38
            ],
            "x_size": 31,
            "x_descenders": 6,
            "x_ascenders": 8
          },
          "text": "Dietz\n      Jacob,\n      butcher,\n      h\n      r\n      420\n      Sixth\n      ry"
        },
        {
          "properties": {
            "bbox": [
              1010,
              2069,
              2253,
              2137
            ],
            "baseline": [
              0,
              -38
            ],
            "x_size": 31,
            "x_descenders": 6,
            "x_ascenders": 8
          },
          "text": "Dietz\n      Jacob,\n      liquors,\n      7\n      Carmine\n      (;"
        },
        {
          "properties": {
            "bbox": [
              1009,
              2108,
              2237,
              2186
            ],
            "baseline": [
              0,
              -55
            ],
            "x_size": 33,
            "x_descenders": 7,
            "x_ascenders": 9
          },
          "text": "Dietz\n      Jacob\n      jr.\n      barber,\n      190\n      Bleecker\n      it\n      ;"
        },
        {
          "properties": {
            "bbox": [
              1008,
              2142,
              2208,
              2203
            ],
            "baseline": [
              0,
              -39
            ],
            "x_size": 31,
            "x_descenders": 7,
            "x_ascenders": 8
          },
          "text": "Dietz\n      James,\n      seaman,\n      h\n      12\n      West\n      jad?"
        },
        {
          "properties": {
            "bbox": [
              1007,
              2174,
              2225,
              2210
            ],
            "baseline": [
              0,
              -13
            ],
            "x_size": 32,
            "x_descenders": 7,
            "x_ascenders": 8
          },
          "text": "Dietz\n      Jane,\n      wid.\n      Herman\n      A.\n      hr\n      141\n      W.\n      28th\n      ."
        },
        {
          "properties": {
            "bbox": [
              1007,
              2207,
              1563,
              2241
            ],
            "baseline": [
              0,
              -11
            ],
            "x_size": 31,
            "x_descenders": 7,
            "x_ascenders": 8
          },
          "text": "Dietz\n      John,\n      brewer,\n      h\n      1018\n      First\n      av."
        },
        {
          "properties": {
            "bbox": [
              1008,
              2240,
              1610,
              2275
            ],
            "baseline": [
              0,
              -12
            ],
            "x_size": 32,
            "x_descenders": 7,
            "x_ascenders": 8
          },
          "text": "Dietz\n      John,\n      cabinetmkr,\n      h\n      367\n      W.\n      85th"
        },
        {
          "properties": {
            "bbox": [
              1007,
              2273,
              2247,
              2320
            ],
            "baseline": [
              0,
              -24
            ],
            "x_size": 32,
            "x_descenders": 7,
            "x_ascenders": 8
          },
          "text": "Dietz\n      John,\n      carpenter,\n      h\n      298\n      Av.\n      A\n      hey"
        },
        {
          "properties": {
            "bbox": [
              1005,
              2306,
              1521,
              2339
            ],
            "baseline": [
              0,
              -9
            ],
            "x_size": 31,
            "x_descenders": 7,
            "x_ascenders": 7
          },
          "text": "Dietz\n      John,\n      driver,\n      h\n      46\n      First\n      av."
        },
        {
          "properties": {
            "bbox": [
              1005,
              2339,
              2253,
              2390
            ],
            "baseline": [
              0,
              -27
            ],
            "x_size": 32,
            "x_descenders": 7,
            "x_ascenders": 8
          },
          "text": "Dietz\n      John,\n      laborer,hr293\n      Av.\n      A\n      i"
        },
        {
          "properties": {
            "bbox": [
              1005,
              2372,
              2252,
              2421
            ],
            "baseline": [
              0,
              -25
            ],
            "x_size": 29,
            "x_descenders": 4,
            "x_ascenders": 8
          },
          "text": "Dietz\n      John\n      F,\n      engineer,\n      h\n      514\n      W.\n      27th\n      :"
        },
        {
          "properties": {
            "bbox": [
              1005,
              2405,
              2253,
              2442
            ],
            "baseline": [
              0,
              -13
            ],
            "x_size": 30,
            "x_descenders": 5,
            "x_ascenders": 8
          },
          "text": "Dietz\n      John\n      G.\n      treas,\n      415\n      EB.\n      10th,\n      h\n      Park\n      av,\n      h.\n      '"
        },
        {
          "properties": {
            "bbox": [
              1004,
              2438,
              1700,
              2475
            ],
            "baseline": [
              0,
              -13
            ],
            "x_size": 31,
            "x_descenders": 6,
            "x_ascenders": 8
          },
          "text": "Dietz\n      Joseph,\n      cabinetmkr.\n      h\n      1413\n      Second\n      av,"
        },
        {
          "properties": {
            "bbox": [
              1003,
              2471,
              1811,
              2508
            ],
            "baseline": [
              0,
              -13
            ],
            "x_size": 29,
            "x_descenders": 4,
            "x_ascenders": 8
          },
          "text": "Dietz\n      Julius\n      jr.\n      meat,\n      175\n      W.\n      48th,\n      hh\n      419\n      W.\n      48th\n      -"
        },
        {
          "properties": {
            "bbox": [
              1002,
              2505,
              1649,
              2538
            ],
            "baseline": [
              0,
              -10
            ],
            "x_size": 32,
            "x_descenders": 7,
            "x_ascenders": 8
          },
          "text": "Dietz\n      Louis,\n      cabinetmkr.\n      h\n      1098\n      Third\n      av."
        },
        {
          "properties": {
            "bbox": [
              1002,
              2538,
              2056,
              2578
            ],
            "baseline": [
              0,
              -16
            ],
            "x_size": 31.763483,
            "x_descenders": 6.763483,
            "x_ascenders": 8
          },
          "text": "Dietz\n      Louisa,\n      dressmkr.\n      832\n      Ninth\n      av.\n      ."
        },
        {
          "properties": {
            "bbox": [
              1001,
              2571,
              1496,
              2604
            ],
            "baseline": [
              0,
              -9
            ],
            "x_size": 32,
            "x_descenders": 7,
            "x_ascenders": 8
          },
          "text": "Dietz\n      Oscar,\n      clerk,\n      h\n      436\n      E.\n      81st"
        },
        {
          "properties": {
            "bbox": [
              1003,
              2605,
              2205,
              2647
            ],
            "baseline": [
              0,
              -19
            ],
            "x_size": 32,
            "x_descenders": 8,
            "x_ascenders": 7
          },
          "text": "Dietz\n      Oscar,\n      jeweler,\n      171\n      Third\n      av,\n      |\n      }"
        },
        {
          "properties": {
            "bbox": [
              1002,
              2637,
              2173,
              2670
            ],
            "baseline": [
              0,
              -9
            ],
            "x_size": 34,
            "x_descenders": 6,
            "x_ascenders": 11
          },
          "text": "Dietz\n      Ottomar,\n      prof.\n      1404\n      Third\n      av.\n      i"
        },
        {
          "properties": {
            "bbox": [
              2170,
              2671,
              2173,
              2686
            ],
            "baseline": [
              0,
              0
            ],
            "x_size": 18.556915,
            "x_descenders": 3.5569148,
            "x_ascenders": 5.1578498
          },
          "text": "}"
        },
        {
          "properties": {
            "bbox": [
              178,
              2662,
              2243,
              2724
            ],
            "baseline": [
              0,
              -39
            ],
            "x_size": 31,
            "x_descenders": 6,
            "x_ascenders": 8
          },
          "text": "Dietrich\n      August,\n      beer,\n      416\n      Sixth\n      Dietz\n      Philip,\n      beer,\n      40\n      Union\n      sq.\n      h\n      193\n      Rivington\n      |\n      ;",
          "columnIndex": 1,
          "completeText": "Dietrich\n      August,\n      beer,\n      416\n      Sixth\n      Dietz\n      Philip,\n      beer,\n      40\n      Union\n      sq.\n      h\n      193\n      Rivington\n      |\n      ;"
        },
        {
          "properties": {
            "bbox": [
              177,
              2695,
              2270,
              2760
            ],
            "baseline": [
              0,
              -43
            ],
            "x_size": 30,
            "x_descenders": 5,
            "x_ascenders": 9
          },
          "text": "Dietrich\n      Barbara,\n      wid.\n      Caspar,\n      h\n      159\n      Third\n      Dietz\n      Philip,\n      pianomkr.\n      h\n      308\n      First\n      av,\n      A\n      >",
          "columnIndex": 1,
          "completeText": "Dietrich\n      Barbara,\n      wid.\n      Caspar,\n      h\n      159\n      Third\n      Dietz\n      Philip,\n      pianomkr.\n      h\n      308\n      First\n      av,\n      A\n      >"
        },
        {
          "properties": {
            "bbox": [
              177,
              2728,
              2273,
              2784
            ],
            "baseline": [
              0,
              -34
            ],
            "x_size": 31,
            "x_descenders": 6,
            "x_ascenders": 8
          },
          "text": "Dietrich\n      Catharine,\n      wid.\n      Adam,\n      h\n      424\n      E.\n      14th\n      Dietz\n      Robert,\n      stables,\n      210\n      W.\n      48th\n      ,",
          "columnIndex": 1,
          "completeText": "Dietrich\n      Catharine,\n      wid.\n      Adam,\n      h\n      424\n      E.\n      14th\n      Dietz\n      Robert,\n      stables,\n      210\n      W.\n      48th\n      ,"
        },
        {
          "properties": {
            "bbox": [
              176,
              2761,
              2287,
              2852
            ],
            "baseline": [
              0,
              -68
            ],
            "x_size": 31,
            "x_descenders": 5,
            "x_ascenders": 9
          },
          "text": "Dietrich\n      Charles\n      A.\n      grocer,\n      319\n      Fifth\n      Dietz\n      Robert\n      E,\n      lanterns,\n      56\n      Fulton,\n      h\n      124\n      W.\n      48th\n      4\n      rh",
          "columnIndex": 1,
          "completeText": "Dietrich\n      Charles\n      A.\n      grocer,\n      319\n      Fifth\n      Dietz\n      Robert\n      E,\n      lanterns,\n      56\n      Fulton,\n      h\n      124\n      W.\n      48th\n      4\n      rh"
        },
        {
          "properties": {
            "bbox": [
              176,
              2794,
              2236,
              2840
            ],
            "baseline": [
              0,
              -23
            ],
            "x_size": 30,
            "x_descenders": 6,
            "x_ascenders": 8
          },
          "text": "Dietrich\n      Chas,\n      F,\n      machinery,\n      414\n      Water,\n      h\n      B'klyn\n      |\n      Dietz\n      Rosa,\n      dressmkr.\n      1404\n      Third\n      av,\n      ia",
          "columnIndex": 1,
          "completeText": "Dietrich\n      Chas,\n      F,\n      machinery,\n      414\n      Water,\n      h\n      B'klyn\n      |\n      Dietz\n      Rosa,\n      dressmkr.\n      1404\n      Third\n      av,\n      ia"
        },
        {
          "properties": {
            "bbox": [
              999,
              2835,
              1589,
              2870
            ],
            "baseline": [
              0,
              -12
            ],
            "x_size": 30,
            "x_descenders": 5,
            "x_ascenders": 9
          },
          "text": "Dietz\n      Rosina,\n      chromos,\n      1314\n      Third\n      av,"
        },
        {
          "properties": {
            "bbox": [
              176,
              2827,
              966,
              2860
            ],
            "baseline": [
              0,
              -10
            ],
            "x_size": 29,
            "x_descenders": 5,
            "x_ascenders": 7
          },
          "text": "Dietrich\n      Christian,\n      segars,\n      58\n      Essex,\n      h\n      172\n      Ludlow",
          "columnIndex": 1,
          "completeText": "Dietrich\n      Christian,\n      segars,\n      58\n      Essex,\n      h\n      172\n      Ludlow"
        },
        {
          "properties": {
            "bbox": [
              1000,
              2868,
              1534,
              2901
            ],
            "baseline": [
              0,
              -10
            ],
            "x_size": 31,
            "x_descenders": 6,
            "x_ascenders": 8
          },
          "text": "Dietz\n      Solomon,\n      meat,\n      h\n      810\n      B.\n      52a"
        },
        {
          "properties": {
            "bbox": [
              176,
              2860,
              965,
              2897
            ],
            "baseline": [
              0,
              -13
            ],
            "x_size": 33,
            "x_descenders": 8,
            "x_ascenders": 8
          },
          "text": "Dietrich\n      Christian,\n      willowware,\n      50\n      Maiden\n      Ja,\n      h",
          "columnIndex": 1,
          "completeText": "Dietrich\n      Christian,\n      willowware,\n      50\n      Maiden\n      Ja,\n      h"
        },
        {
          "properties": {
            "bbox": [
              240,
              2893,
              1575,
              2939
            ],
            "baseline": [
              0,
              -21
            ],
            "x_size": 30,
            "x_descenders": 5,
            "x_ascenders": 8
          },
          "text": "83\n      Henry\n      Dietz\n      Sydingham\n      B.\n      clerk;\n      h\n      11\n      King",
          "columnIndex": 0,
          "completeText": "83\n      Henry\n      Dietz\n      Sydingham\n      B.\n      clerk;\n      h\n      11\n      King"
        },
        {
          "properties": {
            "bbox": [
              174,
              2926,
              1571,
              2972
            ],
            "baseline": [
              0,
              -22
            ],
            "x_size": 31,
            "x_descenders": 7,
            "x_ascenders": 7
          },
          "text": "Dietrich\n      Daniel,\n      barber,\n      29\n      Hester\n      Dietz\n      Theodore,\n      driver,\n      h\n      445\n      W,\n      53d",
          "columnIndex": 1,
          "completeText": "Dietrich\n      Daniel,\n      barber,\n      29\n      Hester\n      Dietz\n      Theodore,\n      driver,\n      h\n      445\n      W,\n      53d"
        },
        {
          "properties": {
            "bbox": [
              174,
              2960,
              1674,
              3003
            ],
            "baseline": [
              0,
              -20
            ],
            "x_size": 28,
            "x_descenders": 4,
            "x_ascenders": 8
          },
          "text": "Deetrich\n      Daniel\n      W.\n      shoes,\n      29\n      Warren,\n      h\n      T..\n      I.\n      Dietz\n      Valentine,\n      bartender,\n      h\n      1479\n      First\n      av.",
          "columnIndex": 1,
          "completeText": "Deetrich\n      Daniel\n      W.\n      shoes,\n      29\n      Warren,\n      h\n      T..\n      I.\n      Dietz\n      Valentine,\n      bartender,\n      h\n      1479\n      First\n      av."
        },
        {
          "properties": {
            "bbox": [
              172,
              2993,
              1629,
              3035
            ],
            "baseline": [
              0,
              -19
            ],
            "x_size": 28,
            "x_descenders": 4,
            "x_ascenders": 7
          },
          "text": "Dietrich\n      Ferdinand,\n      cabinetmkr,\n      h\n      727\n      Third\n      av.\n      Dietz\n      Valentine,\n      segars,\n      796\n      Seventh\n      ay,",
          "columnIndex": 1,
          "completeText": "Dietrich\n      Ferdinand,\n      cabinetmkr,\n      h\n      727\n      Third\n      av.\n      Dietz\n      Valentine,\n      segars,\n      796\n      Seventh\n      ay,"
        },
        {
          "properties": {
            "bbox": [
              173,
              3026,
              1678,
              3072
            ],
            "baseline": [
              0,
              -23
            ],
            "x_size": 30,
            "x_descenders": 6,
            "x_ascenders": 8
          },
          "text": "Dietrich\n      Frederick,\n      clerk.\n      h\n      198\n      Allen\n      Dietz\n      William,\n      florist,\n      254\n      Third\n      av.\n      h\n      N.\n      J,",
          "columnIndex": 1,
          "completeText": "Dietrich\n      Frederick,\n      clerk.\n      h\n      198\n      Allen\n      Dietz\n      William,\n      florist,\n      254\n      Third\n      av.\n      h\n      N.\n      J,"
        },
        {
          "properties": {
            "bbox": [
              172,
              3058,
              1555,
              3099
            ],
            "baseline": [
              0,
              -17
            ],
            "x_size": 30,
            "x_descenders": 6,
            "x_ascenders": 8
          },
          "text": "Dietrich\n      Fred,\n      meat,\n      646\n      Tenth\n      av,\n      h\n      657\n      Tenth\n      av.\n      |\n      Dietz\n      William,\n      meat,\n      924\n      Second\n      ay,",
          "columnIndex": 1,
          "completeText": "Dietrich\n      Fred,\n      meat,\n      646\n      Tenth\n      av,\n      h\n      657\n      Tenth\n      av.\n      |\n      Dietz\n      William,\n      meat,\n      924\n      Second\n      ay,"
        },
        {
          "properties": {
            "bbox": [
              172,
              3092,
              1572,
              3138
            ],
            "baseline": [
              0,
              -22
            ],
            "x_size": 30,
            "x_descenders": 5,
            "x_ascenders": 8
          },
          "text": "Dietrich\n      Frederick,\n      shoes,\n      5U2\n      E,\n      12th\n      Dietz\n      William,\n      porter,\n      h\n      r\n      40\n      Forsyth",
          "columnIndex": 1,
          "completeText": "Dietrich\n      Frederick,\n      shoes,\n      5U2\n      E,\n      12th\n      Dietz\n      William,\n      porter,\n      h\n      r\n      40\n      Forsyth"
        }
      ],
      "columns": [
        219,
        176
      ],
      "linesPerColumn": [
        49,
        37
      ],
      "minLinesPerColumn": false
    }
  ]
}